[{"end-row":16,"meta":{},"name-end-col":13,"name-end-row":16,"name-row":16,"ns":"cljs.nodejs","name":"require","defined-by":"cljs.core/def","git-source":"https://github.com/clojure/clojurescript/blob/r1.11.60/src/main/cljs/cljs/nodejs.cljs#L16","lang":[],"filename":"/src/main/cljs/cljs/nodejs.cljs","col":1,"name-col":6,"end-col":30,"row":16},{"fixed-arities":[0],"end-row":27,"meta":{},"name-end-col":25,"name-end-row":19,"name-row":19,"ns":"cljs.nodejs","name":"enable-util-print!","defined-by":"cljs.core/defn","git-source":"https://github.com/clojure/clojurescript/blob/r1.11.60/src/main/cljs/cljs/nodejs.cljs#L19","lang":[],"filename":"/src/main/cljs/cljs/nodejs.cljs","col":1,"name-col":7,"end-col":7,"arglist-strs":["[]"],"row":19},{"end-row":17,"meta":{},"name-end-col":13,"name-end-row":17,"name-row":17,"ns":"cljs.nodejs","name":"process","defined-by":"cljs.core/def","git-source":"https://github.com/clojure/clojurescript/blob/r1.11.60/src/main/cljs/cljs/nodejs.cljs#L17","lang":[],"filename":"/src/main/cljs/cljs/nodejs.cljs","col":1,"name-col":6,"end-col":30,"row":17}]