[{"fixed-arities":[3],"end-row":23,"meta":null,"name-end-col":18,"name-end-row":20,"private":true,"name-row":20,"ns":"clojure.pprint","name":"use-method","defined-by":"clojure.core/defn-","filename":"clojure/pprint/dispatch.clj","col":1,"name-col":8,"end-col":43,"arglist-strs":["[multifn dispatch-val func]"],"doc":"Installs a function as a new method of multimethod associated with dispatch-value. ","row":20},{"end-row":47,"meta":{"private":true},"name-end-col":36,"name-end-row":45,"private":true,"name-row":45,"ns":"clojure.pprint","name":"reader-macros","defined-by":"clojure.core/def","filename":"clojure/pprint/dispatch.clj","col":1,"name-col":23,"end-col":45,"row":45},{"fixed-arities":[1],"end-row":54,"meta":null,"name-end-col":27,"name-end-row":49,"private":true,"name-row":49,"ns":"clojure.pprint","name":"pprint-reader-macro","defined-by":"clojure.core/defn-","filename":"clojure/pprint/dispatch.clj","col":1,"name-col":8,"end-col":14,"arglist-strs":["[alis]"],"row":49},{"end-row":65,"meta":null,"name-end-col":20,"name-end-row":65,"name-row":65,"ns":"clojure.pprint","name":"pprint-map","defined-by":"clojure.core/declare","filename":"clojure/pprint/dispatch.clj","col":1,"name-col":10,"end-col":21,"row":65},{"fixed-arities":[1],"end-row":73,"meta":null,"name-end-col":19,"name-end-row":67,"private":true,"name-row":67,"ns":"clojure.pprint","name":"pprint-meta","defined-by":"clojure.core/defn-","filename":"clojure/pprint/dispatch.clj","col":1,"name-col":8,"end-col":34,"arglist-strs":["[obj]"],"row":67},{"fixed-arities":[1],"end-row":85,"meta":null,"name-end-col":26,"name-end-row":76,"private":true,"name-row":76,"ns":"clojure.pprint","name":"pprint-simple-list","defined-by":"clojure.core/defn-","filename":"clojure/pprint/dispatch.clj","col":1,"name-col":8,"end-col":28,"arglist-strs":["[alis]"],"row":76},{"fixed-arities":[1],"end-row":89,"meta":null,"name-end-col":19,"name-end-row":87,"private":true,"name-row":87,"ns":"clojure.pprint","name":"pprint-list","defined-by":"clojure.core/defn-","filename":"clojure/pprint/dispatch.clj","col":1,"name-col":8,"end-col":32,"arglist-strs":["[alis]"],"row":87},{"fixed-arities":[1],"end-row":101,"meta":null,"name-end-col":21,"name-end-row":92,"private":true,"name-row":92,"ns":"clojure.pprint","name":"pprint-vector","defined-by":"clojure.core/defn-","filename":"clojure/pprint/dispatch.clj","col":1,"name-col":8,"end-col":28,"arglist-strs":["[avec]"],"row":92},{"end-row":103,"meta":{"private":true},"name-end-col":35,"name-end-row":103,"private":true,"name-row":103,"ns":"clojure.pprint","name":"pprint-array","defined-by":"clojure.core/def","filename":"clojure/pprint/dispatch.clj","col":1,"name-col":23,"end-col":80,"row":103},{"fixed-arities":[1],"end-row":124,"meta":null,"name-end-col":18,"name-end-row":106,"private":true,"name-row":106,"ns":"clojure.pprint","name":"pprint-map","defined-by":"clojure.core/defn-","filename":"clojure/pprint/dispatch.clj","col":1,"name-col":8,"end-col":38,"arglist-strs":["[amap]"],"row":106},{"fixed-arities":[1],"end-row":136,"meta":null,"name-end-col":18,"name-end-row":127,"private":true,"name-row":127,"ns":"clojure.pprint","name":"pprint-set","defined-by":"clojure.core/defn-","filename":"clojure/pprint/dispatch.clj","col":1,"name-col":8,"end-col":35,"arglist-strs":["[aset]"],"row":127},{"end-row":140,"meta":{"private":true},"name-end-col":14,"name-end-row":139,"private":true,"name-row":139,"ns":"clojure.pprint","name":"type-map","defined-by":"clojure.core/def","filename":"clojure/pprint/dispatch.clj","col":1,"name-col":6,"end-col":42,"row":138},{"fixed-arities":[1],"end-row":147,"meta":null,"name-end-col":20,"name-end-row":142,"private":true,"name-row":142,"ns":"clojure.pprint","name":"map-ref-type","defined-by":"clojure.core/defn-","filename":"clojure/pprint/dispatch.clj","col":1,"name-col":8,"end-col":13,"arglist-strs":["[name]"],"doc":"Map ugly type names to something simpler","row":142},{"fixed-arities":[1],"end-row":163,"meta":null,"name-end-col":21,"name-end-row":149,"private":true,"name-row":149,"ns":"clojure.pprint","name":"pprint-ideref","defined-by":"clojure.core/defn-","filename":"clojure/pprint/dispatch.clj","col":1,"name-col":8,"end-col":53,"arglist-strs":["[o]"],"row":149},{"end-row":165,"meta":{"private":true},"name-end-col":36,"name-end-row":165,"private":true,"name-row":165,"ns":"clojure.pprint","name":"pprint-pqueue","defined-by":"clojure.core/def","filename":"clojure/pprint/dispatch.clj","col":1,"name-col":23,"end-col":83,"row":165},{"fixed-arities":[1],"end-row":171,"meta":null,"name-end-col":29,"name-end-row":167,"private":true,"name-row":167,"ns":"clojure.pprint","name":"pprint-simple-default","defined-by":"clojure.core/defn-","filename":"clojure/pprint/dispatch.clj","col":1,"name-col":8,"end-col":21,"arglist-strs":["[obj]"],"row":167},{"end-row":178,"meta":{"added":"1.2","arglists":["quote",[["object"]]]},"name-end-col":18,"name-end-row":175,"name-row":175,"added":"1.2","ns":"clojure.pprint","name":"simple-dispatch","defined-by":"clojure.core/defmulti","filename":"clojure/pprint/dispatch.clj","col":1,"name-col":3,"end-col":9,"doc":"The pretty print dispatch function for simple data structure format.","row":174},{"end-row":194,"meta":null,"name-end-col":33,"name-end-row":194,"name-row":194,"ns":"clojure.pprint","name":"pprint-simple-code-list","defined-by":"clojure.core/declare","filename":"clojure/pprint/dispatch.clj","col":1,"name-col":10,"end-col":34,"row":194},{"fixed-arities":[1],"end-row":207,"meta":null,"name-end-col":16,"name-end-row":202,"private":true,"name-row":202,"ns":"clojure.pprint","name":"brackets","defined-by":"clojure.core/defn-","filename":"clojure/pprint/dispatch.clj","col":1,"name-col":8,"end-col":16,"arglist-strs":["[form]"],"doc":"Figure out which kind of brackets to use","row":202},{"fixed-arities":[1],"end-row":241,"meta":null,"name-end-col":27,"name-end-row":209,"private":true,"name-row":209,"ns":"clojure.pprint","name":"pprint-ns-reference","defined-by":"clojure.core/defn-","filename":"clojure/pprint/dispatch.clj","col":1,"name-col":8,"end-col":45,"arglist-strs":["[reference]"],"doc":"Pretty print a single reference (import, use, etc.) from a namespace decl","row":209},{"fixed-arities":[1],"end-row":267,"meta":null,"name-end-col":17,"name-end-row":243,"private":true,"name-row":243,"ns":"clojure.pprint","name":"pprint-ns","defined-by":"clojure.core/defn-","filename":"clojure/pprint/dispatch.clj","col":1,"name-col":8,"end-col":23,"arglist-strs":["[alis]"],"doc":"The pretty print dispatch chunk for the ns macro","row":243},{"end-row":274,"meta":{"private":true},"name-end-col":40,"name-end-row":274,"private":true,"name-row":274,"ns":"clojure.pprint","name":"pprint-hold-first","defined-by":"clojure.core/def","filename":"clojure/pprint/dispatch.clj","col":1,"name-col":23,"end-col":93,"row":274},{"fixed-arities":[2],"end-row":287,"meta":null,"name-end-col":19,"name-end-row":281,"private":true,"name-row":281,"ns":"clojure.pprint","name":"single-defn","defined-by":"clojure.core/defn-","filename":"clojure/pprint/dispatch.clj","col":1,"name-col":8,"end-col":46,"arglist-strs":["[alis has-doc-str?]"],"row":281},{"fixed-arities":[2],"end-row":292,"meta":null,"name-end-col":18,"name-end-row":290,"private":true,"name-row":290,"ns":"clojure.pprint","name":"multi-defn","defined-by":"clojure.core/defn-","filename":"clojure/pprint/dispatch.clj","col":1,"name-col":8,"end-col":46,"arglist-strs":["[alis has-doc-str?]"],"row":290},{"fixed-arities":[1],"end-row":315,"meta":null,"name-end-col":19,"name-end-row":296,"private":true,"name-row":296,"ns":"clojure.pprint","name":"pprint-defn","defined-by":"clojure.core/defn-","filename":"clojure/pprint/dispatch.clj","col":1,"name-col":8,"end-col":37,"arglist-strs":["[alis]"],"row":296},{"fixed-arities":[1],"end-row":334,"meta":null,"name-end-col":27,"name-end-row":321,"private":true,"name-row":321,"ns":"clojure.pprint","name":"pprint-binding-form","defined-by":"clojure.core/defn-","filename":"clojure/pprint/dispatch.clj","col":1,"name-col":8,"end-col":45,"arglist-strs":["[binding-vec]"],"row":321},{"fixed-arities":[1],"end-row":344,"meta":null,"name-end-col":18,"name-end-row":336,"private":true,"name-row":336,"ns":"clojure.pprint","name":"pprint-let","defined-by":"clojure.core/defn-","filename":"clojure/pprint/dispatch.clj","col":1,"name-col":8,"end-col":43,"arglist-strs":["[alis]"],"row":336},{"end-row":351,"meta":{"private":true},"name-end-col":32,"name-end-row":351,"private":true,"name-row":351,"ns":"clojure.pprint","name":"pprint-if","defined-by":"clojure.core/def","filename":"clojure/pprint/dispatch.clj","col":1,"name-col":23,"end-col":81,"row":351},{"fixed-arities":[1],"end-row":371,"meta":null,"name-end-col":19,"name-end-row":353,"private":true,"name-row":353,"ns":"clojure.pprint","name":"pprint-cond","defined-by":"clojure.core/defn-","filename":"clojure/pprint/dispatch.clj","col":1,"name-col":8,"end-col":44,"arglist-strs":["[alis]"],"row":353},{"fixed-arities":[1],"end-row":390,"meta":null,"name-end-col":20,"name-end-row":373,"private":true,"name-row":373,"ns":"clojure.pprint","name":"pprint-condp","defined-by":"clojure.core/defn-","filename":"clojure/pprint/dispatch.clj","col":1,"name-col":8,"end-col":37,"arglist-strs":["[alis]"],"row":373},{"end-row":393,"meta":{"dynamic":true,"private":true},"name-end-col":45,"name-end-row":393,"private":true,"name-row":393,"ns":"clojure.pprint","name":"*symbol-map*","defined-by":"clojure.core/def","filename":"clojure/pprint/dispatch.clj","col":1,"name-col":33,"end-col":49,"row":393},{"fixed-arities":[1],"end-row":407,"meta":null,"name-end-col":24,"name-end-row":395,"private":true,"name-row":395,"ns":"clojure.pprint","name":"pprint-anon-func","defined-by":"clojure.core/defn-","filename":"clojure/pprint/dispatch.clj","col":1,"name-col":8,"end-col":40,"arglist-strs":["[alis]"],"row":395},{"fixed-arities":[1],"end-row":426,"meta":null,"name-end-col":31,"name-end-row":417,"private":true,"name-row":417,"ns":"clojure.pprint","name":"pprint-simple-code-list","defined-by":"clojure.core/defn-","filename":"clojure/pprint/dispatch.clj","col":1,"name-col":8,"end-col":28,"arglist-strs":["[alis]"],"row":417},{"fixed-arities":[1],"end-row":435,"meta":null,"name-end-col":17,"name-end-row":430,"private":true,"name-row":430,"ns":"clojure.pprint","name":"two-forms","defined-by":"clojure.core/defn-","filename":"clojure/pprint/dispatch.clj","col":1,"name-col":8,"end-col":58,"arglist-strs":["[amap]"],"row":430},{"fixed-arities":[1],"end-row":444,"meta":null,"name-end-col":19,"name-end-row":437,"private":true,"name-row":437,"ns":"clojure.pprint","name":"add-core-ns","defined-by":"clojure.core/defn-","filename":"clojure/pprint/dispatch.clj","col":1,"name-col":8,"end-col":24,"arglist-strs":["[amap]"],"row":437},{"end-row":461,"meta":{"dynamic":true,"private":true},"name-end-col":45,"name-end-row":446,"private":true,"name-row":446,"ns":"clojure.pprint","name":"*code-table*","defined-by":"clojure.core/def","filename":"clojure/pprint/dispatch.clj","col":1,"name-col":33,"end-col":13,"row":446},{"fixed-arities":[1],"end-row":467,"meta":null,"name-end-col":24,"name-end-row":463,"private":true,"name-row":463,"ns":"clojure.pprint","name":"pprint-code-list","defined-by":"clojure.core/defn-","filename":"clojure/pprint/dispatch.clj","col":1,"name-col":8,"end-col":40,"arglist-strs":["[alis]"],"row":463},{"fixed-arities":[1],"end-row":474,"meta":null,"name-end-col":26,"name-end-row":469,"private":true,"name-row":469,"ns":"clojure.pprint","name":"pprint-code-symbol","defined-by":"clojure.core/defn-","filename":"clojure/pprint/dispatch.clj","col":1,"name-col":8,"end-col":18,"arglist-strs":["[sym]"],"row":469},{"end-row":480,"meta":{"added":"1.2","arglists":["quote",[["object"]]]},"name-end-col":16,"name-end-row":477,"name-row":477,"added":"1.2","ns":"clojure.pprint","name":"code-dispatch","defined-by":"clojure.core/defmulti","filename":"clojure/pprint/dispatch.clj","col":1,"name-col":3,"end-col":9,"doc":"The pretty print dispatch function for pretty printing Clojure code.","row":476},{"end-row":30,"meta":null,"name-end-col":25,"name-end-row":30,"name-row":30,"ns":"clojure.pprint","name":"get-miser-width","defined-by":"clojure.core/declare","filename":"clojure/pprint/pretty_writer.clj","col":1,"name-col":10,"end-col":26,"row":30},{"fixed-arities":[1],"end-row":41,"meta":{"private":true},"name-end-col":7,"name-end-row":38,"private":true,"name-row":38,"ns":"clojure.pprint","name":"getf","defined-by":"clojure.core/defmacro","filename":"clojure/pprint/pretty_writer.clj","macro":true,"col":1,"name-col":3,"end-col":20,"arglist-strs":["[sym]"],"doc":"Get the value of the field named by the argument (which should be a keyword).","row":37},{"fixed-arities":[2],"end-row":47,"meta":{"private":true},"name-end-col":7,"name-end-row":44,"private":true,"name-row":44,"ns":"clojure.pprint","name":"setf","defined-by":"clojure.core/defmacro","filename":"clojure/pprint/pretty_writer.clj","macro":true,"col":1,"name-col":3,"end-col":40,"arglist-strs":["[sym new-val]"],"doc":"Set the value of the field SYM to NEW-VAL","row":43},{"end-row":57,"meta":{"private":true},"name-end-col":10,"name-end-row":50,"private":true,"name-row":50,"ns":"clojure.pprint","name":"deftype","defined-by":"clojure.core/defmacro","filename":"clojure/pprint/pretty_writer.clj","macro":true,"col":1,"name-col":3,"end-col":91,"arglist-strs":["[type-name & fields]"],"varargs-min-arity":1,"row":49},{"end-row":65,"meta":{"private":true},"name-end-col":16,"name-end-row":60,"private":true,"name-row":60,"ns":"clojure.pprint","name":"write-to-base","defined-by":"clojure.core/defmacro","filename":"clojure/pprint/pretty_writer.clj","macro":true,"col":1,"name-col":3,"end-col":26,"arglist-strs":["[& args]"],"varargs-min-arity":0,"doc":"Call .write on Writer (getf :base) with proper type-hinting to\n  avoid reflection.","row":59},{"fixed-arities":[2],"end-row":82,"meta":null,"name-end-col":17,"name-end-row":77,"private":true,"name-row":77,"ns":"clojure.pprint","name":"ancestor?","defined-by":"clojure.core/defn-","filename":"clojure/pprint/pretty_writer.clj","col":1,"name-col":8,"end-col":38,"arglist-strs":["[parent child]"],"row":77},{"fixed-arities":[1],"end-row":90,"meta":null,"name-end-col":21,"name-end-row":86,"private":true,"name-row":86,"ns":"clojure.pprint","name":"buffer-length","defined-by":"clojure.core/defn-","filename":"clojure/pprint/pretty_writer.clj","col":1,"name-col":8,"end-col":11,"arglist-strs":["[l]"],"row":86},{"end-row":108,"meta":{"private":true},"name-end-col":26,"name-end-row":108,"private":true,"name-row":108,"ns":"clojure.pprint","name":"pp-newline","defined-by":"clojure.core/def","filename":"clojure/pprint/pretty_writer.clj","col":1,"name-col":16,"end-col":76,"row":108},{"end-row":110,"meta":null,"name-end-col":17,"name-end-row":110,"name-row":110,"ns":"clojure.pprint","name":"emit-nl","defined-by":"clojure.core/declare","filename":"clojure/pprint/pretty_writer.clj","col":1,"name-col":10,"end-col":18,"row":110},{"end-row":112,"meta":{"private":true},"name-end-col":39,"name-end-row":112,"private":true,"name-row":112,"ns":"clojure.pprint","name":"write-token","defined-by":"clojure.core/defmulti","filename":"clojure/pprint/pretty_writer.clj","col":1,"name-col":28,"end-col":56,"row":112},{"fixed-arities":[3],"end-row":160,"meta":null,"name-end-col":20,"name-end-row":150,"private":true,"name-row":150,"ns":"clojure.pprint","name":"write-tokens","defined-by":"clojure.core/defn-","filename":"clojure/pprint/pretty_writer.clj","col":1,"name-col":8,"end-col":42,"arglist-strs":["[this tokens force-trailing-whitespace]"],"row":150},{"fixed-arities":[2],"end-row":173,"meta":null,"name-end-col":19,"name-end-row":168,"private":true,"name-row":168,"ns":"clojure.pprint","name":"tokens-fit?","defined-by":"clojure.core/defn-","filename":"clojure/pprint/pretty_writer.clj","col":1,"name-col":8,"end-col":72,"arglist-strs":["[this tokens]"],"row":168},{"fixed-arities":[3],"end-row":178,"meta":null,"name-end-col":18,"name-end-row":175,"private":true,"name-row":175,"ns":"clojure.pprint","name":"linear-nl?","defined-by":"clojure.core/defn-","filename":"clojure/pprint/pretty_writer.clj","col":1,"name-col":8,"end-col":41,"arglist-strs":["[this lb section]"],"row":175},{"fixed-arities":[3],"end-row":185,"meta":null,"name-end-col":17,"name-end-row":180,"private":true,"name-row":180,"ns":"clojure.pprint","name":"miser-nl?","defined-by":"clojure.core/defn-","filename":"clojure/pprint/pretty_writer.clj","col":1,"name-col":8,"end-col":41,"arglist-strs":["[this lb section]"],"row":180},{"end-row":187,"meta":{"private":true},"name-end-col":36,"name-end-row":187,"private":true,"name-row":187,"ns":"clojure.pprint","name":"emit-nl?","defined-by":"clojure.core/defmulti","filename":"clojure/pprint/pretty_writer.clj","col":1,"name-col":28,"end-col":62,"row":187},{"fixed-arities":[1],"end-row":216,"meta":null,"name-end-col":19,"name-end-row":211,"private":true,"name-row":211,"ns":"clojure.pprint","name":"get-section","defined-by":"clojure.core/defn-","filename":"clojure/pprint/pretty_writer.clj","col":1,"name-col":8,"end-col":58,"arglist-strs":["[buffer]"],"row":211},{"fixed-arities":[1],"end-row":224,"meta":null,"name-end-col":23,"name-end-row":218,"private":true,"name-row":218,"ns":"clojure.pprint","name":"get-sub-section","defined-by":"clojure.core/defn-","filename":"clojure/pprint/pretty_writer.clj","col":1,"name-col":8,"end-col":14,"arglist-strs":["[buffer]"],"row":218},{"fixed-arities":[1],"end-row":234,"meta":null,"name-end-col":23,"name-end-row":226,"private":true,"name-row":226,"ns":"clojure.pprint","name":"update-nl-state","defined-by":"clojure.core/defn-","filename":"clojure/pprint/pretty_writer.clj","col":1,"name-col":8,"end-col":37,"arglist-strs":["[lb]"],"row":226},{"fixed-arities":[2],"end-row":246,"meta":null,"name-end-col":15,"name-end-row":236,"private":true,"name-row":236,"ns":"clojure.pprint","name":"emit-nl","defined-by":"clojure.core/defn-","filename":"clojure/pprint/pretty_writer.clj","col":1,"name-col":8,"end-col":27,"arglist-strs":["[this nl]"],"row":236},{"fixed-arities":[1],"end-row":250,"meta":null,"name-end-col":24,"name-end-row":248,"private":true,"name-row":248,"ns":"clojure.pprint","name":"split-at-newline","defined-by":"clojure.core/defn-","filename":"clojure/pprint/pretty_writer.clj","col":1,"name-col":8,"end-col":44,"arglist-strs":["[tokens]"],"row":248},{"end-row":254,"meta":{"private":true},"name-end-col":31,"name-end-row":254,"private":true,"name-row":254,"ns":"clojure.pprint","name":"tok","defined-by":"clojure.core/defmulti","filename":"clojure/pprint/pretty_writer.clj","col":1,"name-col":28,"end-col":42,"row":254},{"fixed-arities":[1],"end-row":261,"meta":null,"name-end-col":12,"name-end-row":261,"private":true,"name-row":261,"ns":"clojure.pprint","name":"toks","defined-by":"clojure.core/defn-","filename":"clojure/pprint/pretty_writer.clj","col":1,"name-col":8,"end-col":35,"arglist-strs":["[toks]"],"row":261},{"fixed-arities":[2],"end-row":294,"meta":null,"name-end-col":26,"name-end-row":266,"private":true,"name-row":266,"ns":"clojure.pprint","name":"write-token-string","defined-by":"clojure.core/defn-","filename":"clojure/pprint/pretty_writer.clj","col":1,"name-col":8,"end-col":22,"arglist-strs":["[this tokens]"],"row":266},{"fixed-arities":[1],"end-row":305,"meta":null,"name-end-col":18,"name-end-row":296,"private":true,"name-row":296,"ns":"clojure.pprint","name":"write-line","defined-by":"clojure.core/defn-","filename":"clojure/pprint/pretty_writer.clj","col":1,"name-col":8,"end-col":42,"arglist-strs":["[this]"],"row":296},{"fixed-arities":[2],"end-row":314,"meta":null,"name-end-col":21,"name-end-row":309,"private":true,"name-row":309,"ns":"clojure.pprint","name":"add-to-buffer","defined-by":"clojure.core/defn-","filename":"clojure/pprint/pretty_writer.clj","col":1,"name-col":8,"end-col":26,"arglist-strs":["[this token]"],"row":309},{"fixed-arities":[1],"end-row":322,"meta":null,"name-end-col":29,"name-end-row":317,"private":true,"name-row":317,"ns":"clojure.pprint","name":"write-buffered-output","defined-by":"clojure.core/defn-","filename":"clojure/pprint/pretty_writer.clj","col":1,"name-col":8,"end-col":27,"arglist-strs":["[this]"],"row":317},{"fixed-arities":[1],"end-row":329,"meta":null,"name-end-col":25,"name-end-row":324,"private":true,"name-row":324,"ns":"clojure.pprint","name":"write-white-space","defined-by":"clojure.core/defn-","filename":"clojure/pprint/pretty_writer.clj","col":1,"name-col":8,"end-col":41,"arglist-strs":["[this]"],"row":324},{"fixed-arities":[2],"end-row":357,"meta":null,"name-end-col":27,"name-end-row":333,"private":true,"name-row":333,"ns":"clojure.pprint","name":"write-initial-lines","defined-by":"clojure.core/defn-","filename":"clojure/pprint/pretty_writer.clj","col":1,"name-col":8,"end-col":27,"arglist-strs":["[this s]"],"row":333},{"fixed-arities":[2],"end-row":371,"meta":null,"name-end-col":20,"name-end-row":360,"private":true,"name-row":360,"ns":"clojure.pprint","name":"p-write-char","defined-by":"clojure.core/defn-","filename":"clojure/pprint/pretty_writer.clj","col":1,"name-col":8,"end-col":87,"arglist-strs":["[this c]"],"row":360},{"fixed-arities":[3],"end-row":435,"meta":null,"name-end-col":21,"name-end-row":379,"private":true,"name-row":379,"ns":"clojure.pprint","name":"pretty-writer","defined-by":"clojure.core/defn-","filename":"clojure/pprint/pretty_writer.clj","col":1,"name-col":8,"end-col":39,"arglist-strs":["[writer max-columns miser-width]"],"row":379},{"fixed-arities":[4],"end-row":462,"meta":null,"name-end-col":19,"name-end-row":442,"private":true,"name-row":442,"ns":"clojure.pprint","name":"start-block","defined-by":"clojure.core/defn-","filename":"clojure/pprint/pretty_writer.clj","col":1,"name-col":8,"end-col":73,"arglist-strs":["[this prefix per-line-prefix suffix]"],"row":442},{"fixed-arities":[1],"end-row":478,"meta":null,"name-end-col":17,"name-end-row":464,"private":true,"name-row":464,"ns":"clojure.pprint","name":"end-block","defined-by":"clojure.core/defn-","filename":"clojure/pprint/pretty_writer.clj","col":1,"name-col":8,"end-col":44,"arglist-strs":["[this]"],"row":464},{"fixed-arities":[2],"end-row":484,"meta":null,"name-end-col":10,"name-end-row":480,"private":true,"name-row":480,"ns":"clojure.pprint","name":"nl","defined-by":"clojure.core/defn-","filename":"clojure/pprint/pretty_writer.clj","col":1,"name-col":8,"end-col":77,"arglist-strs":["[this type]"],"row":480},{"fixed-arities":[3],"end-row":497,"meta":null,"name-end-col":14,"name-end-row":486,"private":true,"name-row":486,"ns":"clojure.pprint","name":"indent","defined-by":"clojure.core/defn-","filename":"clojure/pprint/pretty_writer.clj","col":1,"name-col":8,"end-col":81,"arglist-strs":["[this relative-to offset]"],"row":486},{"fixed-arities":[1],"end-row":500,"meta":null,"name-end-col":23,"name-end-row":499,"private":true,"name-row":499,"ns":"clojure.pprint","name":"get-miser-width","defined-by":"clojure.core/defn-","filename":"clojure/pprint/pretty_writer.clj","col":1,"name-col":8,"end-col":23,"arglist-strs":["[this]"],"row":499},{"fixed-arities":[2],"end-row":503,"meta":null,"name-end-col":23,"name-end-row":502,"private":true,"name-row":502,"ns":"clojure.pprint","name":"set-miser-width","defined-by":"clojure.core/defn-","filename":"clojure/pprint/pretty_writer.clj","col":1,"name-col":8,"end-col":48,"arglist-strs":["[this new-miser-width]"],"row":502},{"fixed-arities":[2],"end-row":506,"meta":null,"name-end-col":34,"name-end-row":505,"private":true,"name-row":505,"ns":"clojure.pprint","name":"set-logical-block-callback","defined-by":"clojure.core/defn-","filename":"clojure/pprint/pretty_writer.clj","col":1,"name-col":8,"end-col":45,"arglist-strs":["[this f]"],"row":505},{"end-row":22,"meta":null,"name-end-col":24,"name-end-row":22,"name-row":22,"ns":"clojure.pprint","name":"compile-format","defined-by":"clojure.core/declare","filename":"clojure/pprint/cl_format.clj","col":1,"name-col":10,"end-col":25,"row":22},{"end-row":23,"meta":null,"name-end-col":24,"name-end-row":23,"name-row":23,"ns":"clojure.pprint","name":"execute-format","defined-by":"clojure.core/declare","filename":"clojure/pprint/cl_format.clj","col":1,"name-col":10,"end-col":25,"row":23},{"end-row":24,"meta":null,"name-end-col":24,"name-end-row":24,"name-row":24,"ns":"clojure.pprint","name":"init-navigator","defined-by":"clojure.core/declare","filename":"clojure/pprint/cl_format.clj","col":1,"name-col":10,"end-col":25,"row":24},{"end-row":64,"meta":{"added":"1.2","see-also":[["http://www.cs.cmu.edu/afs/cs.cmu.edu/project/ai-repository/ai/html/cltl/clm/node200.html#SECTION002633000000000000000","Common Lisp the Language"],["http://www.lispworks.com/documentation/HyperSpec/Body/22_c.htm","Common Lisp HyperSpec"]]},"name-end-col":16,"name-end-row":27,"name-row":27,"added":"1.2","ns":"clojure.pprint","name":"cl-format","defined-by":"clojure.core/defn","filename":"clojure/pprint/cl_format.clj","col":1,"name-col":7,"end-col":56,"arglist-strs":["[writer format-in & args]"],"varargs-min-arity":2,"doc":"An implementation of a Common Lisp compatible format function. cl-format formats its\narguments to an output stream or string based on the format control string given. It \nsupports sophisticated formatting of structured data.\n\nWriter is an instance of java.io.Writer, true to output to *out* or nil to output \nto a string, format-in is the format control string and the remaining arguments \nare the data to be formatted.\n\nThe format control string is a string to be output with embedded 'format directives' \ndescribing how to format the various arguments passed in.\n\nIf writer is nil, cl-format returns the formatted result string. Otherwise, cl-format \nreturns nil.\n\nFor example:\n (let [results [46 38 22]]\n        (cl-format true \"There ~[are~;is~:;are~]~:* ~d result~:p: ~{~d~^, ~}~%\" \n                   (count results) results))\n\nPrints to *out*:\n There are 3 results: 46, 38, 22\n\nDetailed documentation on format control strings is available in the \"Common Lisp the \nLanguage, 2nd edition\", Chapter 22 (available online at:\nhttp://www.cs.cmu.edu/afs/cs.cmu.edu/project/ai-repository/ai/html/cltl/clm/node200.html#SECTION002633000000000000000) \nand in the Common Lisp HyperSpec at \nhttp://www.lispworks.com/documentation/HyperSpec/Body/22_c.htm\n","row":27},{"end-row":66,"meta":{"dynamic":true,"private":true},"name-end-col":45,"name-end-row":66,"private":true,"name-row":66,"ns":"clojure.pprint","name":"*format-str*","defined-by":"clojure.core/def","filename":"clojure/pprint/cl_format.clj","col":1,"name-col":33,"end-col":50,"row":66},{"fixed-arities":[2],"end-row":71,"meta":null,"name-end-col":20,"name-end-row":68,"private":true,"name-row":68,"ns":"clojure.pprint","name":"format-error","defined-by":"clojure.core/defn-","filename":"clojure/pprint/cl_format.clj","col":1,"name-col":8,"end-col":47,"arglist-strs":["[message offset]"],"row":68},{"fixed-arities":[1],"end-row":87,"meta":{"skip-wiki":true},"name-end-col":22,"name-end-row":82,"private":true,"name-row":82,"ns":"clojure.pprint","name":"init-navigator","defined-by":"clojure.core/defn-","filename":"clojure/pprint/cl_format.clj","col":1,"name-col":8,"end-col":35,"arglist-strs":["[s]"],"doc":"Create a new arg-navigator from the sequence with the position set to 0","row":82},{"fixed-arities":[1],"end-row":94,"meta":null,"name-end-col":16,"name-end-row":90,"private":true,"name-row":90,"ns":"clojure.pprint","name":"next-arg","defined-by":"clojure.core/defn-","filename":"clojure/pprint/cl_format.clj","col":1,"name-col":8,"end-col":78,"arglist-strs":["[navigator]"],"row":90},{"fixed-arities":[1],"end-row":100,"meta":null,"name-end-col":23,"name-end-row":96,"private":true,"name-row":96,"ns":"clojure.pprint","name":"next-arg-or-nil","defined-by":"clojure.core/defn-","filename":"clojure/pprint/cl_format.clj","col":1,"name-col":8,"end-col":25,"arglist-strs":["[navigator]"],"row":96},{"fixed-arities":[1],"end-row":108,"meta":null,"name-end-col":22,"name-end-row":103,"private":true,"name-row":103,"ns":"clojure.pprint","name":"get-format-arg","defined-by":"clojure.core/defn-","filename":"clojure/pprint/cl_format.clj","col":1,"name-col":8,"end-col":34,"arglist-strs":["[navigator]"],"row":103},{"end-row":110,"meta":null,"name-end-col":29,"name-end-row":110,"name-row":110,"ns":"clojure.pprint","name":"relative-reposition","defined-by":"clojure.core/declare","filename":"clojure/pprint/cl_format.clj","col":1,"name-col":10,"end-col":30,"row":110},{"fixed-arities":[2],"end-row":115,"meta":null,"name-end-col":27,"name-end-row":112,"private":true,"name-row":112,"ns":"clojure.pprint","name":"absolute-reposition","defined-by":"clojure.core/defn-","filename":"clojure/pprint/cl_format.clj","col":1,"name-col":8,"end-col":88,"arglist-strs":["[navigator position]"],"row":112},{"fixed-arities":[2],"end-row":121,"meta":null,"name-end-col":27,"name-end-row":117,"private":true,"name-row":117,"ns":"clojure.pprint","name":"relative-reposition","defined-by":"clojure.core/defn-","filename":"clojure/pprint/cl_format.clj","col":1,"name-col":8,"end-col":90,"arglist-strs":["[navigator position]"],"row":117},{"fixed-arities":[2],"end-row":148,"meta":null,"name-end-col":25,"name-end-row":134,"private":true,"name-row":134,"ns":"clojure.pprint","name":"realize-parameter","defined-by":"clojure.core/defn-","filename":"clojure/pprint/cl_format.clj","col":1,"name-col":8,"end-col":50,"arglist-strs":["[[param [raw-val offset]] navigator]"],"row":134},{"fixed-arities":[2],"end-row":153,"meta":null,"name-end-col":30,"name-end-row":150,"private":true,"name-row":150,"ns":"clojure.pprint","name":"realize-parameter-list","defined-by":"clojure.core/defn-","filename":"clojure/pprint/cl_format.clj","col":1,"name-col":8,"end-col":38,"arglist-strs":["[parameter-map navigator]"],"row":150},{"end-row":163,"meta":null,"name-end-col":22,"name-end-row":163,"name-row":163,"ns":"clojure.pprint","name":"opt-base-str","defined-by":"clojure.core/declare","filename":"clojure/pprint/cl_format.clj","col":1,"name-col":10,"end-col":23,"row":163},{"end-row":166,"meta":{"private":true},"name-end-col":27,"name-end-row":166,"private":true,"name-row":166,"ns":"clojure.pprint","name":"special-radix-markers","defined-by":"clojure.core/def","filename":"clojure/pprint/cl_format.clj","col":1,"name-col":6,"end-col":53,"row":165},{"fixed-arities":[1],"end-row":180,"meta":null,"name-end-col":28,"name-end-row":168,"private":true,"name-row":168,"ns":"clojure.pprint","name":"format-simple-number","defined-by":"clojure.core/defn-","filename":"clojure/pprint/cl_format.clj","col":1,"name-col":8,"end-col":16,"arglist-strs":["[n]"],"row":168},{"fixed-arities":[4],"end-row":198,"meta":null,"name-end-col":20,"name-end-row":182,"private":true,"name-row":182,"ns":"clojure.pprint","name":"format-ascii","defined-by":"clojure.core/defn-","filename":"clojure/pprint/cl_format.clj","col":1,"name-col":8,"end-col":20,"arglist-strs":["[print-func params arg-navigator offsets]"],"row":182},{"fixed-arities":[1],"end-row":214,"meta":null,"name-end-col":17,"name-end-row":205,"private":true,"name-row":205,"ns":"clojure.pprint","name":"integral?","defined-by":"clojure.core/defn-","filename":"clojure/pprint/cl_format.clj","col":1,"name-col":8,"end-col":24,"arglist-strs":["[x]"],"doc":"returns true if a number is actually an integer (that is, has no fractional part)","row":205},{"fixed-arities":[2],"end-row":224,"meta":null,"name-end-col":18,"name-end-row":216,"private":true,"name-row":216,"ns":"clojure.pprint","name":"remainders","defined-by":"clojure.core/defn-","filename":"clojure/pprint/cl_format.clj","col":1,"name-col":8,"end-col":21,"arglist-strs":["[base val]"],"doc":"Return the list of remainders (essentially the 'digits') of val in the given base","row":216},{"fixed-arities":[2],"end-row":240,"meta":null,"name-end-col":16,"name-end-row":227,"private":true,"name-row":227,"ns":"clojure.pprint","name":"base-str","defined-by":"clojure.core/defn-","filename":"clojure/pprint/cl_format.clj","col":1,"name-col":8,"end-col":41,"arglist-strs":["[base val]"],"doc":"Return val as a string in the given base","row":227},{"end-row":243,"meta":{"private":true},"name-end-col":23,"name-end-row":243,"private":true,"name-row":243,"ns":"clojure.pprint","name":"java-base-formats","defined-by":"clojure.core/def","filename":"clojure/pprint/cl_format.clj","col":1,"name-col":6,"end-col":51,"row":242},{"fixed-arities":[2],"end-row":252,"meta":null,"name-end-col":20,"name-end-row":245,"private":true,"name-row":245,"ns":"clojure.pprint","name":"opt-base-str","defined-by":"clojure.core/defn-","filename":"clojure/pprint/cl_format.clj","col":1,"name-col":8,"end-col":29,"arglist-strs":["[base val]"],"doc":"Return val as a string in the given base, using clojure.core/format if supported\nfor improved performance","row":245},{"fixed-arities":[2],"end-row":257,"meta":null,"name-end-col":17,"name-end-row":254,"private":true,"name-row":254,"ns":"clojure.pprint","name":"group-by*","defined-by":"clojure.core/defn-","filename":"clojure/pprint/cl_format.clj","col":1,"name-col":8,"end-col":92,"arglist-strs":["[unit lis]"],"row":254},{"fixed-arities":[4],"end-row":283,"meta":null,"name-end-col":22,"name-end-row":259,"private":true,"name-row":259,"ns":"clojure.pprint","name":"format-integer","defined-by":"clojure.core/defn-","filename":"clojure/pprint/cl_format.clj","col":1,"name-col":8,"end-col":20,"arglist-strs":["[base params arg-navigator offsets]"],"row":259},{"end-row":293,"meta":{"private":true},"name-end-col":28,"name-end-row":290,"private":true,"name-row":290,"ns":"clojure.pprint","name":"english-cardinal-units","defined-by":"clojure.core/def","filename":"clojure/pprint/cl_format.clj","col":1,"name-col":6,"end-col":62,"row":289},{"end-row":299,"meta":{"private":true},"name-end-col":27,"name-end-row":296,"private":true,"name-row":296,"ns":"clojure.pprint","name":"english-ordinal-units","defined-by":"clojure.core/def","filename":"clojure/pprint/cl_format.clj","col":1,"name-col":6,"end-col":72,"row":295},{"end-row":303,"meta":{"private":true},"name-end-col":27,"name-end-row":302,"private":true,"name-row":302,"ns":"clojure.pprint","name":"english-cardinal-tens","defined-by":"clojure.core/def","filename":"clojure/pprint/cl_format.clj","col":1,"name-col":6,"end-col":84,"row":301},{"end-row":308,"meta":{"private":true},"name-end-col":26,"name-end-row":306,"private":true,"name-row":306,"ns":"clojure.pprint","name":"english-ordinal-tens","defined-by":"clojure.core/def","filename":"clojure/pprint/cl_format.clj","col":1,"name-col":6,"end-col":56,"row":305},{"end-row":320,"meta":{"private":true},"name-end-col":27,"name-end-row":315,"private":true,"name-row":315,"ns":"clojure.pprint","name":"english-scale-numbers","defined-by":"clojure.core/def","filename":"clojure/pprint/cl_format.clj","col":1,"name-col":6,"end-col":56,"row":314},{"fixed-arities":[1],"end-row":338,"meta":null,"name-end-col":30,"name-end-row":322,"private":true,"name-row":322,"ns":"clojure.pprint","name":"format-simple-cardinal","defined-by":"clojure.core/defn-","filename":"clojure/pprint/cl_format.clj","col":1,"name-col":8,"end-col":82,"arglist-strs":["[num]"],"doc":"Convert a number less than 1000 to a cardinal english string","row":322},{"fixed-arities":[2],"end-row":361,"meta":null,"name-end-col":26,"name-end-row":340,"private":true,"name-row":340,"ns":"clojure.pprint","name":"add-english-scales","defined-by":"clojure.core/defn-","filename":"clojure/pprint/cl_format.clj","col":1,"name-col":8,"end-col":31,"arglist-strs":["[parts offset]"],"doc":"Take a sequence of parts, add scale numbers (e.g., million) and combine into a string\noffset is a factor of 10^3 to multiply by","row":340},{"fixed-arities":[3],"end-row":378,"meta":null,"name-end-col":31,"name-end-row":363,"private":true,"name-row":363,"ns":"clojure.pprint","name":"format-cardinal-english","defined-by":"clojure.core/defn-","filename":"clojure/pprint/cl_format.clj","col":1,"name-col":8,"end-col":16,"arglist-strs":["[params navigator offsets]"],"row":363},{"fixed-arities":[1],"end-row":400,"meta":null,"name-end-col":29,"name-end-row":380,"private":true,"name-row":380,"ns":"clojure.pprint","name":"format-simple-ordinal","defined-by":"clojure.core/defn-","filename":"clojure/pprint/cl_format.clj","col":1,"name-col":8,"end-col":37,"arglist-strs":["[num]"],"doc":"Convert a number less than 1000 to a ordinal english string\nNote this should only be used for the last one in the sequence","row":380},{"fixed-arities":[3],"end-row":432,"meta":null,"name-end-col":30,"name-end-row":402,"private":true,"name-row":402,"ns":"clojure.pprint","name":"format-ordinal-english","defined-by":"clojure.core/defn-","filename":"clojure/pprint/cl_format.clj","col":1,"name-col":8,"end-col":16,"arglist-strs":["[params navigator offsets]"],"row":402},{"end-row":444,"meta":{"private":true},"name-end-col":21,"name-end-row":440,"private":true,"name-row":440,"ns":"clojure.pprint","name":"old-roman-table","defined-by":"clojure.core/def","filename":"clojure/pprint/cl_format.clj","col":1,"name-col":6,"end-col":26,"row":439},{"end-row":451,"meta":{"private":true},"name-end-col":21,"name-end-row":447,"private":true,"name-row":447,"ns":"clojure.pprint","name":"new-roman-table","defined-by":"clojure.core/def","filename":"clojure/pprint/cl_format.clj","col":1,"name-col":6,"end-col":26,"row":446},{"fixed-arities":[4],"end-row":475,"meta":null,"name-end-col":20,"name-end-row":453,"private":true,"name-row":453,"ns":"clojure.pprint","name":"format-roman","defined-by":"clojure.core/defn-","filename":"clojure/pprint/cl_format.clj","col":1,"name-col":8,"end-col":16,"arglist-strs":["[table params navigator offsets]"],"doc":"Format a roman numeral using the specified look-up table","row":453},{"fixed-arities":[3],"end-row":478,"meta":null,"name-end-col":24,"name-end-row":477,"private":true,"name-row":477,"ns":"clojure.pprint","name":"format-old-roman","defined-by":"clojure.core/defn-","filename":"clojure/pprint/cl_format.clj","col":1,"name-col":8,"end-col":59,"arglist-strs":["[params navigator offsets]"],"row":477},{"fixed-arities":[3],"end-row":481,"meta":null,"name-end-col":24,"name-end-row":480,"private":true,"name-row":480,"ns":"clojure.pprint","name":"format-new-roman","defined-by":"clojure.core/defn-","filename":"clojure/pprint/cl_format.clj","col":1,"name-col":8,"end-col":59,"arglist-strs":["[params navigator offsets]"],"row":480},{"end-row":488,"meta":{"private":true},"name-end-col":19,"name-end-row":488,"private":true,"name-row":488,"ns":"clojure.pprint","name":"special-chars","defined-by":"clojure.core/def","filename":"clojure/pprint/cl_format.clj","col":1,"name-col":6,"end-col":86,"row":487},{"fixed-arities":[3],"end-row":502,"meta":null,"name-end-col":24,"name-end-row":490,"private":true,"name-row":490,"ns":"clojure.pprint","name":"pretty-character","defined-by":"clojure.core/defn-","filename":"clojure/pprint/cl_format.clj","col":1,"name-col":8,"end-col":16,"arglist-strs":["[params navigator offsets]"],"row":490},{"fixed-arities":[3],"end-row":510,"meta":null,"name-end-col":26,"name-end-row":504,"private":true,"name-row":504,"ns":"clojure.pprint","name":"readable-character","defined-by":"clojure.core/defn-","filename":"clojure/pprint/cl_format.clj","col":1,"name-col":8,"end-col":16,"arglist-strs":["[params navigator offsets]"],"row":504},{"fixed-arities":[3],"end-row":515,"meta":null,"name-end-col":23,"name-end-row":512,"private":true,"name-row":512,"ns":"clojure.pprint","name":"plain-character","defined-by":"clojure.core/defn-","filename":"clojure/pprint/cl_format.clj","col":1,"name-col":8,"end-col":16,"arglist-strs":["[params navigator offsets]"],"row":512},{"fixed-arities":[1],"end-row":521,"meta":null,"name-end-col":14,"name-end-row":519,"private":true,"name-row":519,"ns":"clojure.pprint","name":"abort?","defined-by":"clojure.core/defn-","filename":"clojure/pprint/cl_format.clj","col":1,"name-col":8,"end-col":57,"arglist-strs":["[context]"],"row":519},{"fixed-arities":[3],"end-row":535,"meta":null,"name-end-col":26,"name-end-row":524,"private":true,"name-row":524,"ns":"clojure.pprint","name":"execute-sub-format","defined-by":"clojure.core/defn-","filename":"clojure/pprint/cl_format.clj","col":1,"name-col":8,"end-col":14,"arglist-strs":["[format args base-args]"],"row":524},{"fixed-arities":[1],"end-row":554,"meta":null,"name-end-col":24,"name-end-row":542,"private":true,"name-row":542,"ns":"clojure.pprint","name":"float-parts-base","defined-by":"clojure.core/defn-","filename":"clojure/pprint/cl_format.clj","col":1,"name-col":8,"end-col":73,"arglist-strs":["[f]"],"doc":"Produce string parts for the mantissa (normalized 1-9) and exponent","row":542},{"fixed-arities":[1],"end-row":567,"meta":null,"name-end-col":19,"name-end-row":557,"private":true,"name-row":557,"ns":"clojure.pprint","name":"float-parts","defined-by":"clojure.core/defn-","filename":"clojure/pprint/cl_format.clj","col":1,"name-col":8,"end-col":44,"arglist-strs":["[f]"],"doc":"Take care of leading and trailing zeros in decomposed floats","row":557},{"fixed-arities":[1],"end-row":583,"meta":{"tag":"String"},"name-end-col":21,"name-end-row":569,"private":true,"name-row":569,"ns":"clojure.pprint","name":"inc-s","defined-by":"clojure.core/defn-","filename":"clojure/pprint/cl_format.clj","col":1,"name-col":16,"end-col":50,"arglist-strs":["[s]"],"doc":"Assumption: The input string consists of one or more decimal digits,\nand no other characters.  Return a string containing one or more\ndecimal digits containing a decimal number one larger than the input\nstring.  The output string will always be the same length as the input\nstring, or one character longer.","row":569},{"fixed-arities":[4],"end-row":625,"meta":null,"name-end-col":17,"name-end-row":585,"private":true,"name-row":585,"ns":"clojure.pprint","name":"round-str","defined-by":"clojure.core/defn-","filename":"clojure/pprint/cl_format.clj","col":1,"name-col":8,"end-col":18,"arglist-strs":["[m e d w]"],"row":585},{"fixed-arities":[3],"end-row":635,"meta":null,"name-end-col":20,"name-end-row":627,"private":true,"name-row":627,"ns":"clojure.pprint","name":"expand-fixed","defined-by":"clojure.core/defn-","filename":"clojure/pprint/cl_format.clj","col":1,"name-col":8,"end-col":12,"arglist-strs":["[m e d]"],"row":627},{"fixed-arities":[2],"end-row":643,"meta":null,"name-end-col":22,"name-end-row":637,"private":true,"name-row":637,"ns":"clojure.pprint","name":"insert-decimal","defined-by":"clojure.core/defn-","filename":"clojure/pprint/cl_format.clj","col":1,"name-col":8,"end-col":47,"arglist-strs":["[m e]"],"doc":"Insert the decimal point at the right spot in the number to match an exponent","row":637},{"fixed-arities":[3],"end-row":646,"meta":null,"name-end-col":17,"name-end-row":645,"private":true,"name-row":645,"ns":"clojure.pprint","name":"get-fixed","defined-by":"clojure.core/defn-","filename":"clojure/pprint/cl_format.clj","col":1,"name-col":8,"end-col":43,"arglist-strs":["[m e d]"],"row":645},{"fixed-arities":[2],"end-row":653,"meta":null,"name-end-col":29,"name-end-row":648,"private":true,"name-row":648,"ns":"clojure.pprint","name":"insert-scaled-decimal","defined-by":"clojure.core/defn-","filename":"clojure/pprint/cl_format.clj","col":1,"name-col":8,"end-col":40,"arglist-strs":["[m k]"],"doc":"Insert the decimal point at the right spot in the number to match an exponent","row":648},{"fixed-arities":[1],"end-row":668,"meta":null,"name-end-col":21,"name-end-row":655,"private":true,"name-row":655,"ns":"clojure.pprint","name":"convert-ratio","defined-by":"clojure.core/defn-","filename":"clojure/pprint/cl_format.clj","col":1,"name-col":8,"end-col":8,"arglist-strs":["[x]"],"row":655},{"fixed-arities":[3],"end-row":714,"meta":null,"name-end-col":19,"name-end-row":672,"private":true,"name-row":672,"ns":"clojure.pprint","name":"fixed-float","defined-by":"clojure.core/defn-","filename":"clojure/pprint/cl_format.clj","col":1,"name-col":8,"end-col":16,"arglist-strs":["[params navigator offsets]"],"row":672},{"fixed-arities":[3],"end-row":787,"meta":null,"name-end-col":25,"name-end-row":720,"private":true,"name-row":720,"ns":"clojure.pprint","name":"exponential-float","defined-by":"clojure.core/defn-","filename":"clojure/pprint/cl_format.clj","col":1,"name-col":8,"end-col":16,"arglist-strs":["[params navigator offsets]"],"row":720},{"fixed-arities":[3],"end-row":813,"meta":null,"name-end-col":21,"name-end-row":794,"private":true,"name-row":794,"ns":"clojure.pprint","name":"general-float","defined-by":"clojure.core/defn-","filename":"clojure/pprint/cl_format.clj","col":1,"name-col":8,"end-col":54,"arglist-strs":["[params navigator offsets]"],"row":794},{"fixed-arities":[3],"end-row":833,"meta":null,"name-end-col":20,"name-end-row":817,"private":true,"name-row":817,"ns":"clojure.pprint","name":"dollar-float","defined-by":"clojure.core/defn-","filename":"clojure/pprint/cl_format.clj","col":1,"name-col":8,"end-col":16,"arglist-strs":["[params navigator offsets]"],"row":817},{"fixed-arities":[3],"end-row":852,"meta":null,"name-end-col":26,"name-end-row":843,"private":true,"name-row":843,"ns":"clojure.pprint","name":"choice-conditional","defined-by":"clojure.core/defn-","filename":"clojure/pprint/cl_format.clj","col":1,"name-col":8,"end-col":19,"arglist-strs":["[params arg-navigator offsets]"],"row":843},{"fixed-arities":[3],"end-row":863,"meta":null,"name-end-col":27,"name-end-row":855,"private":true,"name-row":855,"ns":"clojure.pprint","name":"boolean-conditional","defined-by":"clojure.core/defn-","filename":"clojure/pprint/cl_format.clj","col":1,"name-col":8,"end-col":19,"arglist-strs":["[params arg-navigator offsets]"],"row":855},{"fixed-arities":[3],"end-row":875,"meta":null,"name-end-col":29,"name-end-row":867,"private":true,"name-row":867,"ns":"clojure.pprint","name":"check-arg-conditional","defined-by":"clojure.core/defn-","filename":"clojure/pprint/cl_format.clj","col":1,"name-col":8,"end-col":19,"arglist-strs":["[params arg-navigator offsets]"],"row":867},{"fixed-arities":[3],"end-row":907,"meta":null,"name-end-col":23,"name-end-row":886,"private":true,"name-row":886,"ns":"clojure.pprint","name":"iterate-sublist","defined-by":"clojure.core/defn-","filename":"clojure/pprint/cl_format.clj","col":1,"name-col":8,"end-col":62,"arglist-strs":["[params navigator offsets]"],"row":886},{"fixed-arities":[3],"end-row":930,"meta":null,"name-end-col":32,"name-end-row":911,"private":true,"name-row":911,"ns":"clojure.pprint","name":"iterate-list-of-sublists","defined-by":"clojure.core/defn-","filename":"clojure/pprint/cl_format.clj","col":1,"name-col":8,"end-col":54,"arglist-strs":["[params navigator offsets]"],"row":911},{"fixed-arities":[3],"end-row":954,"meta":null,"name-end-col":25,"name-end-row":934,"private":true,"name-row":934,"ns":"clojure.pprint","name":"iterate-main-list","defined-by":"clojure.core/defn-","filename":"clojure/pprint/cl_format.clj","col":1,"name-col":8,"end-col":61,"arglist-strs":["[params navigator offsets]"],"row":934},{"fixed-arities":[3],"end-row":975,"meta":null,"name-end-col":29,"name-end-row":958,"private":true,"name-row":958,"ns":"clojure.pprint","name":"iterate-main-sublists","defined-by":"clojure.core/defn-","filename":"clojure/pprint/cl_format.clj","col":1,"name-col":8,"end-col":48,"arglist-strs":["[params navigator offsets]"],"row":958},{"end-row":990,"meta":null,"name-end-col":30,"name-end-row":990,"name-row":990,"ns":"clojure.pprint","name":"format-logical-block","defined-by":"clojure.core/declare","filename":"clojure/pprint/cl_format.clj","col":1,"name-col":10,"end-col":31,"row":990},{"end-row":991,"meta":null,"name-end-col":25,"name-end-row":991,"name-row":991,"ns":"clojure.pprint","name":"justify-clauses","defined-by":"clojure.core/declare","filename":"clojure/pprint/cl_format.clj","col":1,"name-col":10,"end-col":26,"row":991},{"fixed-arities":[3],"end-row":996,"meta":null,"name-end-col":32,"name-end-row":993,"private":true,"name-row":993,"ns":"clojure.pprint","name":"logical-block-or-justify","defined-by":"clojure.core/defn-","filename":"clojure/pprint/cl_format.clj","col":1,"name-col":8,"end-col":49,"arglist-strs":["[params navigator offsets]"],"row":993},{"fixed-arities":[3],"end-row":1014,"meta":null,"name-end-col":22,"name-end-row":1002,"private":true,"name-row":1002,"ns":"clojure.pprint","name":"render-clauses","defined-by":"clojure.core/defn-","filename":"clojure/pprint/cl_format.clj","col":1,"name-col":8,"end-col":72,"arglist-strs":["[clauses navigator base-navigator]"],"row":1002},{"fixed-arities":[3],"end-row":1062,"meta":null,"name-end-col":23,"name-end-row":1017,"private":true,"name-row":1017,"ns":"clojure.pprint","name":"justify-clauses","defined-by":"clojure.core/defn-","filename":"clojure/pprint/cl_format.clj","col":1,"name-col":8,"end-col":16,"arglist-strs":["[params navigator offsets]"],"row":1017},{"fixed-arities":[1],"end-row":1088,"meta":null,"name-end-col":23,"name-end-row":1072,"private":true,"name-row":1072,"ns":"clojure.pprint","name":"downcase-writer","defined-by":"clojure.core/defn-","filename":"clojure/pprint/cl_format.clj","col":1,"name-col":8,"end-col":65,"arglist-strs":["[writer]"],"doc":"Returns a proxy that wraps writer, converting all characters to lower case","row":1072},{"fixed-arities":[1],"end-row":1106,"meta":null,"name-end-col":21,"name-end-row":1090,"private":true,"name-row":1090,"ns":"clojure.pprint","name":"upcase-writer","defined-by":"clojure.core/defn-","filename":"clojure/pprint/cl_format.clj","col":1,"name-col":8,"end-col":65,"arglist-strs":["[writer]"],"doc":"Returns a proxy that wraps writer, converting all characters to upper case","row":1090},{"fixed-arities":[2],"end-row":1130,"meta":null,"name-end-col":25,"name-end-row":1108,"private":true,"name-row":1108,"ns":"clojure.pprint","name":"capitalize-string","defined-by":"clojure.core/defn-","filename":"clojure/pprint/cl_format.clj","col":1,"name-col":8,"end-col":20,"arglist-strs":["[s first?]"],"doc":"Capitalizes the words in a string. If first? is false, don't capitalize the \n                                      first character of the string even if it's a letter.","row":1108},{"fixed-arities":[1],"end-row":1158,"meta":null,"name-end-col":30,"name-end-row":1132,"private":true,"name-row":1132,"ns":"clojure.pprint","name":"capitalize-word-writer","defined-by":"clojure.core/defn-","filename":"clojure/pprint/cl_format.clj","col":1,"name-col":8,"end-col":98,"arglist-strs":["[writer]"],"doc":"Returns a proxy that wraps writer, capitalizing all words","row":1132},{"fixed-arities":[1],"end-row":1192,"meta":null,"name-end-col":23,"name-end-row":1160,"private":true,"name-row":1160,"ns":"clojure.pprint","name":"init-cap-writer","defined-by":"clojure.core/defn-","filename":"clojure/pprint/cl_format.clj","col":1,"name-col":8,"end-col":77,"arglist-strs":["[writer]"],"doc":"Returns a proxy that wraps writer, capitalizing the first word","row":1160},{"fixed-arities":[4],"end-row":1197,"meta":null,"name-end-col":19,"name-end-row":1194,"private":true,"name-row":1194,"ns":"clojure.pprint","name":"modify-case","defined-by":"clojure.core/defn-","filename":"clojure/pprint/cl_format.clj","col":1,"name-col":8,"end-col":67,"arglist-strs":["[make-writer params navigator offsets]"],"row":1194},{"fixed-arities":[1],"end-row":1239,"meta":{"added":"1.2"},"name-end-col":24,"name-end-row":1203,"name-row":1203,"added":"1.2","ns":"clojure.pprint","name":"get-pretty-writer","defined-by":"clojure.core/defn","filename":"clojure/pprint/cl_format.clj","col":1,"name-col":7,"end-col":70,"arglist-strs":["[writer]"],"doc":"Returns the java.io.Writer passed in wrapped in a pretty writer proxy, unless it's \nalready a pretty writer. Generally, it is unnecessary to call this function, since pprint,\nwrite, and cl-format all call it if they need to. However if you want the state to be \npreserved across calls, you will want to wrap them with this. \n\nFor example, when you want to generate column-aware output with multiple calls to cl-format, \ndo it like in this example:\n\n    (defn print-table [aseq column-width]\n      (binding [*out* (get-pretty-writer *out*)]\n        (doseq [row aseq]\n          (doseq [col row]\n            (cl-format true \"~4D~7,vT\" col column-width))\n          (prn))))\n\nNow when you run:\n\n    user> (print-table (map #(vector % (* % %) (* % % %)) (range 1 11)) 8)\n\nIt prints a table of squares and cubes for the numbers from 1 to 10:\n\n       1      1       1    \n       2      4       8    \n       3      9      27    \n       4     16      64    \n       5     25     125    \n       6     36     216    \n       7     49     343    \n       8     64     512    \n       9     81     729    \n      10    100    1000","row":1203},{"fixed-arities":[0],"end-row":1253,"meta":{"added":"1.2"},"name-end-col":17,"name-end-row":1245,"name-row":1245,"added":"1.2","ns":"clojure.pprint","name":"fresh-line","defined-by":"clojure.core/defn","filename":"clojure/pprint/cl_format.clj","col":1,"name-col":7,"end-col":12,"arglist-strs":["[]"],"doc":"Make a newline if *out* is not already at the beginning of the line. If *out* is\nnot a pretty writer (which keeps track of columns), this function always outputs a newline.","row":1245},{"fixed-arities":[3],"end-row":1264,"meta":null,"name-end-col":27,"name-end-row":1255,"private":true,"name-row":1255,"ns":"clojure.pprint","name":"absolute-tabulation","defined-by":"clojure.core/defn-","filename":"clojure/pprint/cl_format.clj","col":1,"name-col":8,"end-col":13,"arglist-strs":["[params navigator offsets]"],"row":1255},{"fixed-arities":[3],"end-row":1273,"meta":null,"name-end-col":27,"name-end-row":1266,"private":true,"name-row":1266,"ns":"clojure.pprint","name":"relative-tabulation","defined-by":"clojure.core/defn-","filename":"clojure/pprint/cl_format.clj","col":1,"name-col":8,"end-col":13,"arglist-strs":["[params navigator offsets]"],"row":1266},{"fixed-arities":[3],"end-row":1298,"meta":null,"name-end-col":28,"name-end-row":1282,"private":true,"name-row":1282,"ns":"clojure.pprint","name":"format-logical-block","defined-by":"clojure.core/defn-","filename":"clojure/pprint/cl_format.clj","col":1,"name-col":8,"end-col":16,"arglist-strs":["[params navigator offsets]"],"row":1282},{"fixed-arities":[3],"end-row":1303,"meta":null,"name-end-col":18,"name-end-row":1300,"private":true,"name-row":1300,"ns":"clojure.pprint","name":"set-indent","defined-by":"clojure.core/defn-","filename":"clojure/pprint/cl_format.clj","col":1,"name-col":8,"end-col":16,"arglist-strs":["[params navigator offsets]"],"row":1300},{"fixed-arities":[3],"end-row":1312,"meta":null,"name-end-col":27,"name-end-row":1307,"private":true,"name-row":1307,"ns":"clojure.pprint","name":"conditional-newline","defined-by":"clojure.core/defn-","filename":"clojure/pprint/cl_format.clj","col":1,"name-col":8,"end-col":16,"arglist-strs":["[params navigator offsets]"],"row":1307},{"fixed-arities":[1],"end-row":1326,"meta":null,"name-end-col":39,"name-end-row":1320,"private":true,"name-row":1320,"ns":"clojure.pprint","name":"process-directive-table-element","defined-by":"clojure.core/defn-","filename":"clojure/pprint/cl_format.clj","col":1,"name-col":8,"end-col":67,"arglist-strs":["[[char params flags bracket-info & generator-fn]]"],"row":1320},{"end-row":1332,"meta":{"private":true},"name-end-col":16,"name-end-row":1329,"private":true,"name-row":1329,"ns":"clojure.pprint","name":"defdirectives","defined-by":"clojure.core/defmacro","filename":"clojure/pprint/cl_format.clj","macro":true,"col":1,"name-col":3,"end-col":91,"arglist-strs":["[& directives]"],"varargs-min-arity":0,"row":1328},{"end-row":1621,"meta":{"private":true},"name-end-col":19,"name-end-row":1621,"private":true,"name-row":1621,"ns":"clojure.pprint","name":"param-pattern","defined-by":"clojure.core/def","filename":"clojure/pprint/cl_format.clj","col":1,"name-col":6,"end-col":55,"row":1620},{"end-row":1623,"meta":{"private":true},"name-end-col":20,"name-end-row":1623,"private":true,"name-row":1623,"ns":"clojure.pprint","name":"special-params","defined-by":"clojure.core/def","filename":"clojure/pprint/cl_format.clj","col":1,"name-col":6,"end-col":68,"row":1622},{"fixed-arities":[1],"end-row":1637,"meta":null,"name-end-col":21,"name-end-row":1625,"private":true,"name-row":1625,"ns":"clojure.pprint","name":"extract-param","defined-by":"clojure.core/defn-","filename":"clojure/pprint/cl_format.clj","col":1,"name-col":8,"end-col":30,"arglist-strs":["[[s offset saw-comma]]"],"row":1625},{"fixed-arities":[2],"end-row":1641,"meta":null,"name-end-col":22,"name-end-row":1640,"private":true,"name-row":1640,"ns":"clojure.pprint","name":"extract-params","defined-by":"clojure.core/defn-","filename":"clojure/pprint/cl_format.clj","col":1,"name-col":8,"end-col":44,"arglist-strs":["[s offset]"],"row":1640},{"fixed-arities":[1],"end-row":1653,"meta":null,"name-end-col":23,"name-end-row":1643,"private":true,"name-row":1643,"ns":"clojure.pprint","name":"translate-param","defined-by":"clojure.core/defn-","filename":"clojure/pprint/cl_format.clj","col":1,"name-col":8,"end-col":12,"arglist-strs":["[[p offset]]"],"doc":"Translate the string representation of a param to the internalized\n                                      representation","row":1643},{"end-row":1656,"meta":{"private":true},"name-end-col":15,"name-end-row":1656,"private":true,"name-row":1656,"ns":"clojure.pprint","name":"flag-defs","defined-by":"clojure.core/def","filename":"clojure/pprint/cl_format.clj","col":1,"name-col":6,"end-col":38,"row":1655},{"fixed-arities":[2],"end-row":1671,"meta":null,"name-end-col":21,"name-end-row":1658,"private":true,"name-row":1658,"ns":"clojure.pprint","name":"extract-flags","defined-by":"clojure.core/defn-","filename":"clojure/pprint/cl_format.clj","col":1,"name-col":8,"end-col":19,"arglist-strs":["[s offset]"],"row":1658},{"fixed-arities":[2],"end-row":1684,"meta":null,"name-end-col":19,"name-end-row":1673,"private":true,"name-row":1673,"ns":"clojure.pprint","name":"check-flags","defined-by":"clojure.core/defn-","filename":"clojure/pprint/cl_format.clj","col":1,"name-col":8,"end-col":73,"arglist-strs":["[def flags]"],"row":1673},{"fixed-arities":[4],"end-row":1714,"meta":null,"name-end-col":18,"name-end-row":1686,"private":true,"name-row":1686,"ns":"clojure.pprint","name":"map-params","defined-by":"clojure.core/defn-","filename":"clojure/pprint/cl_format.clj","col":1,"name-col":8,"end-col":11,"arglist-strs":["[def params flags offset]"],"doc":"Takes a directive definition and the list of actual parameters and\na map of flags and returns a map of the parameters and flags with defaults\nfilled in. We check to make sure that there are the right types and number\nof parameters as well.","row":1686},{"fixed-arities":[2],"end-row":1734,"meta":null,"name-end-col":25,"name-end-row":1716,"private":true,"name-row":1716,"ns":"clojure.pprint","name":"compile-directive","defined-by":"clojure.core/defn-","filename":"clojure/pprint/cl_format.clj","col":1,"name-col":8,"end-col":30,"arglist-strs":["[s offset]"],"row":1716},{"fixed-arities":[2],"end-row":1737,"meta":null,"name-end-col":26,"name-end-row":1736,"private":true,"name-row":1736,"ns":"clojure.pprint","name":"compile-raw-string","defined-by":"clojure.core/defn-","filename":"clojure/pprint/cl_format.clj","col":1,"name-col":8,"end-col":81,"arglist-strs":["[s offset]"],"row":1736},{"fixed-arities":[1],"end-row":1739,"meta":null,"name-end-col":21,"name-end-row":1739,"private":true,"name-row":1739,"ns":"clojure.pprint","name":"right-bracket","defined-by":"clojure.core/defn-","filename":"clojure/pprint/cl_format.clj","col":1,"name-col":8,"end-col":66,"arglist-strs":["[this]"],"row":1739},{"fixed-arities":[1],"end-row":1740,"meta":null,"name-end-col":18,"name-end-row":1740,"private":true,"name-row":1740,"ns":"clojure.pprint","name":"separator?","defined-by":"clojure.core/defn-","filename":"clojure/pprint/cl_format.clj","col":1,"name-col":8,"end-col":67,"arglist-strs":["[this]"],"row":1740},{"fixed-arities":[1],"end-row":1743,"meta":null,"name-end-col":23,"name-end-row":1741,"private":true,"name-row":1741,"ns":"clojure.pprint","name":"else-separator?","defined-by":"clojure.core/defn-","filename":"clojure/pprint/cl_format.clj","col":1,"name-col":8,"end-col":33,"arglist-strs":["[this]"],"row":1741},{"end-row":1746,"meta":null,"name-end-col":25,"name-end-row":1746,"name-row":1746,"ns":"clojure.pprint","name":"collect-clauses","defined-by":"clojure.core/declare","filename":"clojure/pprint/cl_format.clj","col":1,"name-col":10,"end-col":26,"row":1746},{"fixed-arities":[2],"end-row":1755,"meta":null,"name-end-col":23,"name-end-row":1748,"private":true,"name-row":1748,"ns":"clojure.pprint","name":"process-bracket","defined-by":"clojure.core/defn-","filename":"clojure/pprint/cl_format.clj","col":1,"name-col":8,"end-col":18,"arglist-strs":["[this remainder]"],"row":1748},{"fixed-arities":[3],"end-row":1779,"meta":null,"name-end-col":22,"name-end-row":1757,"private":true,"name-row":1757,"ns":"clojure.pprint","name":"process-clause","defined-by":"clojure.core/defn-","filename":"clojure/pprint/cl_format.clj","col":1,"name-col":8,"end-col":15,"arglist-strs":["[bracket-info offset remainder]"],"row":1757},{"fixed-arities":[3],"end-row":1828,"meta":null,"name-end-col":23,"name-end-row":1781,"private":true,"name-row":1781,"ns":"clojure.pprint","name":"collect-clauses","defined-by":"clojure.core/defn-","filename":"clojure/pprint/cl_format.clj","col":1,"name-col":8,"end-col":41,"arglist-strs":["[bracket-info offset remainder]"],"row":1781},{"fixed-arities":[1],"end-row":1843,"meta":null,"name-end-col":23,"name-end-row":1830,"private":true,"name-row":1830,"ns":"clojure.pprint","name":"process-nesting","defined-by":"clojure.core/defn-","filename":"clojure/pprint/cl_format.clj","col":1,"name-col":8,"end-col":14,"arglist-strs":["[format]"],"doc":"Take a linearly compiled format and process the bracket directives to give it \n   the appropriate tree structure","row":1830},{"fixed-arities":[1],"end-row":1864,"meta":null,"name-end-col":22,"name-end-row":1845,"private":true,"name-row":1845,"ns":"clojure.pprint","name":"compile-format","defined-by":"clojure.core/defn-","filename":"clojure/pprint/cl_format.clj","col":1,"name-col":8,"end-col":27,"arglist-strs":["[format-str]"],"doc":"Compiles format-str into a compiled format which can be used as an argument\nto cl-format just like a plain format string. Use this function for improved \nperformance when you're using the same format string repeatedly","row":1845},{"fixed-arities":[1],"end-row":1877,"meta":null,"name-end-col":20,"name-end-row":1866,"private":true,"name-row":1866,"ns":"clojure.pprint","name":"needs-pretty","defined-by":"clojure.core/defn-","filename":"clojure/pprint/cl_format.clj","col":1,"name-col":8,"end-col":34,"arglist-strs":["[format]"],"doc":"determine whether a given compiled format has any directives that depend on the\ncolumn number or pretty printing","row":1866},{"fixed-arities":[3,2],"end-row":1910,"meta":{"skip-wiki":true},"name-end-col":22,"name-end-row":1879,"private":true,"name-row":1879,"ns":"clojure.pprint","name":"execute-format","defined-by":"clojure.core/defn-","filename":"clojure/pprint/cl_format.clj","col":1,"name-col":8,"end-col":11,"arglist-strs":["[stream format args]","[format args]"],"doc":"Executes the format with the arguments.","row":1879},{"end-row":1914,"meta":{"private":true},"name-end-col":37,"name-end-row":1914,"private":true,"name-row":1914,"ns":"clojure.pprint","name":"cached-compile","defined-by":"clojure.core/def","filename":"clojure/pprint/cl_format.clj","col":1,"name-col":23,"end-col":63,"row":1914},{"fixed-arities":[1],"end-row":1934,"meta":{"added":"1.2"},"name-end-col":20,"name-end-row":1916,"name-row":1916,"added":"1.2","ns":"clojure.pprint","name":"formatter","defined-by":"clojure.core/defmacro","filename":"clojure/pprint/cl_format.clj","macro":true,"col":1,"name-col":11,"end-col":46,"arglist-strs":["[format-in]"],"doc":"Makes a function which can directly run format-in. The function is\nfn [stream & args] ... and returns nil unless the stream is nil (meaning \noutput to a string) in which case it returns the resulting string.\n\nformat-in can be either a control string or a previously compiled format.","row":1916},{"fixed-arities":[1],"end-row":1949,"meta":{"added":"1.2"},"name-end-col":24,"name-end-row":1936,"name-row":1936,"added":"1.2","ns":"clojure.pprint","name":"formatter-out","defined-by":"clojure.core/defmacro","filename":"clojure/pprint/cl_format.clj","macro":true,"col":1,"name-col":11,"end-col":62,"arglist-strs":["[format-in]"],"doc":"Makes a function which can directly run format-in. The function is\nfn [& args] ... and returns nil. This version of the formatter macro is\ndesigned to be used with *out* set to an appropriate Writer. In particular,\nthis is meant to be used as part of a pretty printer dispatch method.\n\nformat-in can be either a control string or a previously compiled format.","row":1936},{"end-row":32,"meta":{"dynamic":true,"added":"1.2","doc":"Bind to true if you want write to use pretty printing"},"name-end-col":16,"name-end-row":32,"name-row":32,"added":"1.2","ns":"clojure.pprint","name":"*print-pretty*","defined-by":"clojure.core/def","filename":"clojure/pprint/pprint_base.clj","col":1,"name-col":2,"end-col":22,"doc":"Bind to true if you want write to use pretty printing","row":30},{"end-row":38,"meta":{"dynamic":true,"added":"1.2","doc":"The pretty print dispatch function. Use with-pprint-dispatch or set-pprint-dispatch\nto modify."},"name-end-col":25,"name-end-row":38,"name-row":38,"added":"1.2","ns":"clojure.pprint","name":"*print-pprint-dispatch*","defined-by":"clojure.core/defonce","filename":"clojure/pprint/pprint_base.clj","col":1,"name-col":2,"end-col":30,"doc":"The pretty print dispatch function. Use with-pprint-dispatch or set-pprint-dispatch\nto modify.","row":34},{"end-row":45,"meta":{"dynamic":true,"added":"1.2","doc":"Pretty printing will try to avoid anything going beyond this column.\nSet it to nil to have pprint let the line be arbitrarily long. This will ignore all \nnon-mandatory newlines."},"name-end-col":22,"name-end-row":45,"name-row":45,"added":"1.2","ns":"clojure.pprint","name":"*print-right-margin*","defined-by":"clojure.core/def","filename":"clojure/pprint/pprint_base.clj","col":1,"name-col":2,"end-col":26,"doc":"Pretty printing will try to avoid anything going beyond this column.\nSet it to nil to have pprint let the line be arbitrarily long. This will ignore all \nnon-mandatory newlines.","row":40},{"end-row":52,"meta":{"dynamic":true,"added":"1.2","doc":"The column at which to enter miser style. Depending on the dispatch table, \nmiser style add newlines in more places to try to keep lines short allowing for further \nlevels of nesting."},"name-end-col":21,"name-end-row":52,"name-row":52,"added":"1.2","ns":"clojure.pprint","name":"*print-miser-width*","defined-by":"clojure.core/def","filename":"clojure/pprint/pprint_base.clj","col":1,"name-col":2,"end-col":25,"doc":"The column at which to enter miser style. Depending on the dispatch table, \nmiser style add newlines in more places to try to keep lines short allowing for further \nlevels of nesting.","row":47},{"end-row":58,"meta":{"dynamic":true,"private":true,"doc":"Maximum number of lines to print in a pretty print instance (N.B. This is not yet used)"},"name-end-col":15,"name-end-row":58,"private":true,"name-row":58,"ns":"clojure.pprint","name":"*print-lines*","defined-by":"clojure.core/def","filename":"clojure/pprint/pprint_base.clj","col":1,"name-col":2,"end-col":20,"doc":"Maximum number of lines to print in a pretty print instance (N.B. This is not yet used)","row":55},{"end-row":64,"meta":{"dynamic":true,"private":true,"doc":"Mark circular structures (N.B. This is not yet used)"},"name-end-col":16,"name-end-row":64,"private":true,"name-row":64,"ns":"clojure.pprint","name":"*print-circle*","defined-by":"clojure.core/def","filename":"clojure/pprint/pprint_base.clj","col":1,"name-col":2,"end-col":21,"doc":"Mark circular structures (N.B. This is not yet used)","row":61},{"end-row":70,"meta":{"dynamic":true,"private":true,"doc":"Mark repeated structures rather than repeat them (N.B. This is not yet used)"},"name-end-col":16,"name-end-row":70,"private":true,"name-row":70,"ns":"clojure.pprint","name":"*print-shared*","defined-by":"clojure.core/def","filename":"clojure/pprint/pprint_base.clj","col":1,"name-col":2,"end-col":21,"doc":"Mark repeated structures rather than repeat them (N.B. This is not yet used)","row":67},{"end-row":76,"meta":{"dynamic":true,"added":"1.2","doc":"Don't print namespaces with symbols. This is particularly useful when \npretty printing the results of macro expansions"},"name-end-col":29,"name-end-row":76,"name-row":76,"added":"1.2","ns":"clojure.pprint","name":"*print-suppress-namespaces*","defined-by":"clojure.core/def","filename":"clojure/pprint/pprint_base.clj","col":1,"name-col":2,"end-col":34,"doc":"Don't print namespaces with symbols. This is particularly useful when \npretty printing the results of macro expansions","row":72},{"end-row":85,"meta":{"dynamic":true,"added":"1.2","doc":"Print a radix specifier in front of integers and rationals. If *print-base* is 2, 8, \nor 16, then the radix specifier used is #b, #o, or #x, respectively. Otherwise the \nradix specifier is in the form #XXr where XX is the decimal value of *print-base* "},"name-end-col":15,"name-end-row":85,"name-row":85,"added":"1.2","ns":"clojure.pprint","name":"*print-radix*","defined-by":"clojure.core/def","filename":"clojure/pprint/pprint_base.clj","col":1,"name-col":2,"end-col":20,"doc":"Print a radix specifier in front of integers and rationals. If *print-base* is 2, 8, \nor 16, then the radix specifier used is #b, #o, or #x, respectively. Otherwise the \nradix specifier is in the form #XXr where XX is the decimal value of *print-base* ","row":80},{"end-row":90,"meta":{"dynamic":true,"added":"1.2","doc":"The base to use for printing integers and rationals."},"name-end-col":14,"name-end-row":90,"name-row":90,"added":"1.2","ns":"clojure.pprint","name":"*print-base*","defined-by":"clojure.core/def","filename":"clojure/pprint/pprint_base.clj","col":1,"name-col":2,"end-col":18,"doc":"The base to use for printing integers and rationals.","row":87},{"end-row":99,"meta":{"dynamic":true,"private":true},"name-end-col":51,"name-end-row":99,"private":true,"name-row":99,"ns":"clojure.pprint","name":"*current-level*","defined-by":"clojure.core/def","filename":"clojure/pprint/pprint_base.clj","col":1,"name-col":36,"end-col":54,"row":99},{"end-row":101,"meta":{"dynamic":true,"private":true},"name-end-col":51,"name-end-row":101,"private":true,"name-row":101,"ns":"clojure.pprint","name":"*current-length*","defined-by":"clojure.core/def","filename":"clojure/pprint/pprint_base.clj","col":1,"name-col":35,"end-col":56,"row":101},{"end-row":109,"meta":null,"name-end-col":30,"name-end-row":109,"name-row":109,"ns":"clojure.pprint","name":"format-simple-number","defined-by":"clojure.core/declare","filename":"clojure/pprint/pprint_base.clj","col":1,"name-col":10,"end-col":31,"row":109},{"end-row":111,"meta":{"private":true},"name-end-col":30,"name-end-row":111,"private":true,"name-row":111,"ns":"clojure.pprint","name":"orig-pr","defined-by":"clojure.core/def","filename":"clojure/pprint/pprint_base.clj","col":1,"name-col":23,"end-col":34,"row":111},{"fixed-arities":[1],"end-row":116,"meta":null,"name-end-col":20,"name-end-row":113,"private":true,"name-row":113,"ns":"clojure.pprint","name":"pr-with-base","defined-by":"clojure.core/defn-","filename":"clojure/pprint/pprint_base.clj","col":1,"name-col":8,"end-col":18,"arglist-strs":["[x]"],"row":113},{"end-row":134,"meta":{"private":true},"name-end-col":41,"name-end-row":118,"private":true,"name-row":118,"ns":"clojure.pprint","name":"write-option-table","defined-by":"clojure.core/def","filename":"clojure/pprint/pprint_base.clj","col":1,"name-col":23,"end-col":73,"row":118},{"end-row":144,"meta":{"private":true},"name-end-col":39,"name-end-row":137,"private":true,"name-row":137,"ns":"clojure.pprint","name":"binding-map","defined-by":"clojure.core/defmacro","filename":"clojure/pprint/pprint_base.clj","macro":true,"col":1,"name-col":28,"end-col":55,"arglist-strs":["[amap & body]"],"varargs-min-arity":1,"row":137},{"fixed-arities":[2],"end-row":149,"meta":null,"name-end-col":17,"name-end-row":146,"private":true,"name-row":146,"ns":"clojure.pprint","name":"table-ize","defined-by":"clojure.core/defn-","filename":"clojure/pprint/pprint_base.clj","col":1,"name-col":8,"end-col":24,"arglist-strs":["[t m]"],"row":146},{"fixed-arities":[1],"end-row":153,"meta":null,"name-end-col":22,"name-end-row":151,"private":true,"name-row":151,"ns":"clojure.pprint","name":"pretty-writer?","defined-by":"clojure.core/defn-","filename":"clojure/pprint/pprint_base.clj","col":1,"name-col":8,"end-col":68,"arglist-strs":["[x]"],"doc":"Return true iff x is a PrettyWriter","row":151},{"fixed-arities":[3],"end-row":158,"meta":null,"name-end-col":26,"name-end-row":155,"private":true,"name-row":155,"ns":"clojure.pprint","name":"make-pretty-writer","defined-by":"clojure.core/defn-","filename":"clojure/pprint/pprint_base.clj","col":1,"name-col":8,"end-col":56,"arglist-strs":["[base-writer right-margin miser-width]"],"doc":"Wrap base-writer in a PrettyWriter with the specified right-margin and miser-width","row":155},{"end-row":167,"meta":{"private":true},"name-end-col":46,"name-end-row":160,"private":true,"name-row":160,"ns":"clojure.pprint","name":"with-pretty-writer","defined-by":"clojure.core/defmacro","filename":"clojure/pprint/pprint_base.clj","macro":true,"col":1,"name-col":28,"end-col":40,"arglist-strs":["[base-writer & body]"],"varargs-min-arity":1,"row":160},{"fixed-arities":[1],"end-row":195,"meta":{"added":"1.2"},"name-end-col":16,"name-end-row":171,"name-row":171,"added":"1.2","ns":"clojure.pprint","name":"write-out","defined-by":"clojure.core/defn","filename":"clojure/pprint/pprint_base.clj","col":1,"name-col":7,"end-col":21,"arglist-strs":["[object]"],"doc":"Write an object to *out* subject to the current bindings of the printer control \nvariables. Use the kw-args argument to override individual variables for this call (and \nany recursive calls).\n\n*out* must be a PrettyWriter if pretty printing is enabled. This is the responsibility\nof the caller.\n\nThis method is primarily intended for use by pretty print dispatch functions that \nalready know that the pretty printer will have set up their environment appropriately.\nNormal library clients should use the standard \"write\" interface. ","row":171},{"end-row":238,"meta":{"added":"1.2"},"name-end-col":12,"name-end-row":197,"name-row":197,"added":"1.2","ns":"clojure.pprint","name":"write","defined-by":"clojure.core/defn","filename":"clojure/pprint/pprint_base.clj","col":1,"name-col":7,"end-col":64,"arglist-strs":["[object & kw-args]"],"varargs-min-arity":1,"doc":"Write an object subject to the current bindings of the printer control variables.\nUse the kw-args argument to override individual variables for this call (and any \nrecursive calls). Returns the string result if :stream is nil or nil otherwise.\n\nThe following keyword arguments can be passed with values:\n  Keyword              Meaning                              Default value\n  :stream              Writer for output or nil             true (indicates *out*)\n  :base                Base to use for writing rationals    Current value of *print-base*\n  :circle*             If true, mark circular structures    Current value of *print-circle*\n  :length              Maximum elements to show in sublists Current value of *print-length*\n  :level               Maximum depth                        Current value of *print-level*\n  :lines*              Maximum lines of output              Current value of *print-lines*\n  :miser-width         Width to enter miser mode            Current value of *print-miser-width*\n  :dispatch            The pretty print dispatch function   Current value of *print-pprint-dispatch*\n  :pretty              If true, do pretty printing          Current value of *print-pretty*\n  :radix               If true, prepend a radix specifier   Current value of *print-radix*\n  :readably*           If true, print readably              Current value of *print-readably*\n  :right-margin        The column for the right margin      Current value of *print-right-margin*\n  :suppress-namespaces If true, no namespaces in symbols    Current value of *print-suppress-namespaces*\n\n  * = not yet supported\n","row":197},{"fixed-arities":[1,2],"end-row":252,"meta":{"added":"1.2"},"name-end-col":13,"name-end-row":241,"name-row":241,"added":"1.2","ns":"clojure.pprint","name":"pprint","defined-by":"clojure.core/defn","filename":"clojure/pprint/pprint_base.clj","col":1,"name-col":7,"end-col":19,"arglist-strs":["[object]","[object writer]"],"doc":"Pretty print object to the optional output writer. If the writer is not provided, \nprint the object to the currently bound value of *out*.","row":241},{"fixed-arities":[0],"end-row":258,"meta":{"added":"1.2"},"name-end-col":13,"name-end-row":254,"name-row":254,"added":"1.2","ns":"clojure.pprint","name":"pp","defined-by":"clojure.core/defmacro","filename":"clojure/pprint/pprint_base.clj","macro":true,"col":1,"name-col":11,"end-col":19,"arglist-strs":["[]"],"doc":"A convenience macro that pretty prints the last thing output. This is\nexactly equivalent to (pprint *1).","row":254},{"fixed-arities":[1],"end-row":272,"meta":{"added":"1.2"},"name-end-col":26,"name-end-row":260,"name-row":260,"added":"1.2","ns":"clojure.pprint","name":"set-pprint-dispatch","defined-by":"clojure.core/defn","filename":"clojure/pprint/pprint_base.clj","col":1,"name-col":7,"end-col":7,"arglist-strs":["[function]"],"doc":"Set the pretty print dispatch function to a function matching (fn [obj] ...)\nwhere obj is the object to pretty print. That function will be called with *out* set\nto a pretty printing writer to which it should do its printing.\n\nFor example functions, see simple-dispatch and code-dispatch in \nclojure.pprint.dispatch.clj.","row":260},{"end-row":279,"meta":{"added":"1.2"},"name-end-col":31,"name-end-row":274,"name-row":274,"added":"1.2","ns":"clojure.pprint","name":"with-pprint-dispatch","defined-by":"clojure.core/defmacro","filename":"clojure/pprint/pprint_base.clj","macro":true,"col":1,"name-col":11,"end-col":14,"arglist-strs":["[function & body]"],"varargs-min-arity":1,"doc":"Execute body with the pretty print dispatch function bound to function.","row":274},{"fixed-arities":[2],"end-row":290,"meta":null,"name-end-col":24,"name-end-row":285,"private":true,"name-row":285,"ns":"clojure.pprint","name":"parse-lb-options","defined-by":"clojure.core/defn-","filename":"clojure/pprint/pprint_base.clj","col":1,"name-col":8,"end-col":37,"arglist-strs":["[opts body]"],"row":285},{"fixed-arities":[2],"end-row":297,"meta":null,"name-end-col":28,"name-end-row":292,"private":true,"name-row":292,"ns":"clojure.pprint","name":"check-enumerated-arg","defined-by":"clojure.core/defn-","filename":"clojure/pprint/pprint_base.clj","col":1,"name-col":8,"end-col":74,"arglist-strs":["[arg choices]"],"row":292},{"fixed-arities":[0],"end-row":300,"meta":null,"name-end-col":22,"name-end-row":299,"private":true,"name-row":299,"ns":"clojure.pprint","name":"level-exceeded","defined-by":"clojure.core/defn-","filename":"clojure/pprint/pprint_base.clj","col":1,"name-col":8,"end-col":58,"arglist-strs":["[]"],"row":299},{"end-row":327,"meta":{"added":"1.2","arglists":["quote",[["options*","body"]]]},"name-end-col":31,"name-end-row":302,"name-row":302,"added":"1.2","ns":"clojure.pprint","name":"pprint-logical-block","defined-by":"clojure.core/defmacro","filename":"clojure/pprint/pprint_base.clj","macro":true,"col":1,"name-col":11,"end-col":16,"arglist-strs":["[& args]"],"varargs-min-arity":0,"doc":"Execute the body as a pretty printing logical block with output to *out* which \nmust be a pretty printing writer. When used from pprint or cl-format, this can be \nassumed. \n\nThis function is intended for use when writing custom dispatch functions.\n\nBefore the body, the caller can optionally specify options: :prefix, :per-line-prefix, \nand :suffix.","row":302},{"fixed-arities":[1],"end-row":339,"meta":{"added":"1.2"},"name-end-col":21,"name-end-row":329,"name-row":329,"added":"1.2","ns":"clojure.pprint","name":"pprint-newline","defined-by":"clojure.core/defn","filename":"clojure/pprint/pprint_base.clj","col":1,"name-col":7,"end-col":19,"arglist-strs":["[kind]"],"doc":"Print a conditional newline to a pretty printing stream. kind specifies if the \nnewline is :linear, :miser, :fill, or :mandatory. \n\nThis function is intended for use when writing custom dispatch functions.\n\nOutput is sent to *out* which must be a pretty printing writer.","row":329},{"fixed-arities":[2],"end-row":353,"meta":{"added":"1.2"},"name-end-col":20,"name-end-row":341,"name-row":341,"added":"1.2","ns":"clojure.pprint","name":"pprint-indent","defined-by":"clojure.core/defn","filename":"clojure/pprint/pprint_base.clj","col":1,"name-col":7,"end-col":32,"arglist-strs":["[relative-to n]"],"doc":"Create an indent at this point in the pretty printing stream. This defines how \nfollowing lines are indented. relative-to can be either :block or :current depending \nwhether the indent should be computed relative to the start of the logical block or\nthe current column position. n is an offset. \n\nThis function is intended for use when writing custom dispatch functions.\n\nOutput is sent to *out* which must be a pretty printing writer.","row":341},{"fixed-arities":[3],"end-row":371,"meta":{"added":"1.2"},"name-end-col":17,"name-end-row":356,"name-row":356,"added":"1.2","ns":"clojure.pprint","name":"pprint-tab","defined-by":"clojure.core/defn","filename":"clojure/pprint/pprint_base.clj","col":1,"name-col":7,"end-col":80,"arglist-strs":["[kind colnum colinc]"],"doc":"Tab at this point in the pretty printing stream. kind specifies whether the tab\nis :line, :section, :line-relative, or :section-relative. \n\nColnum and colinc specify the target column and the increment to move the target\nforward if the output is already past the original target.\n\nThis function is intended for use when writing custom dispatch functions.\n\nOutput is sent to *out* which must be a pretty printing writer.\n\nTHIS FUNCTION IS NOT YET IMPLEMENTED.","row":356},{"fixed-arities":[2],"end-row":389,"meta":null,"name-end-col":20,"name-end-row":380,"private":true,"name-row":380,"ns":"clojure.pprint","name":"pll-mod-body","defined-by":"clojure.core/defn-","filename":"clojure/pprint/pprint_base.clj","col":1,"name-col":8,"end-col":33,"arglist-strs":["[var-sym body]"],"row":380},{"end-row":401,"meta":{"added":"1.3"},"name-end-col":28,"name-end-row":391,"name-row":391,"added":"1.3","ns":"clojure.pprint","name":"print-length-loop","defined-by":"clojure.core/defmacro","filename":"clojure/pprint/pprint_base.clj","macro":true,"col":1,"name-col":11,"end-col":50,"arglist-strs":["[bindings & body]"],"varargs-min-arity":1,"doc":"A version of loop that iterates at most *print-length* times. This is designed \nfor use in pretty-printer dispatch functions.","row":391},{"fixed-arities":[1,2],"end-row":35,"meta":{"added":"1.3"},"name-end-col":18,"name-end-row":11,"name-row":11,"added":"1.3","ns":"clojure.pprint","name":"print-table","defined-by":"clojure.core/defn","filename":"clojure/pprint/print_table.clj","col":1,"name-col":7,"end-col":51,"arglist-strs":["[ks rows]","[rows]"],"doc":"Prints a collection of maps in a textual table. Prints table headings\n   ks, and then a line of output for each row, corresponding to the keys\n   in ks. If ks are not specified, use the keys of the first item in rows.","row":11},{"fixed-arities":[3],"end-row":35,"meta":null,"name-end-col":27,"name-end-row":26,"private":true,"name-row":26,"ns":"clojure.pprint","name":"map-passing-context","defined-by":"clojure.core/defn-","filename":"clojure/pprint/utilities.clj","col":1,"name-col":8,"end-col":58,"arglist-strs":["[func initial-context lis]"],"row":26},{"fixed-arities":[2],"end-row":43,"meta":null,"name-end-col":15,"name-end-row":37,"private":true,"name-row":37,"ns":"clojure.pprint","name":"consume","defined-by":"clojure.core/defn-","filename":"clojure/pprint/utilities.clj","col":1,"name-col":8,"end-col":48,"arglist-strs":["[func initial-context]"],"row":37},{"fixed-arities":[2],"end-row":51,"meta":null,"name-end-col":21,"name-end-row":45,"private":true,"name-row":45,"ns":"clojure.pprint","name":"consume-while","defined-by":"clojure.core/defn-","filename":"clojure/pprint/utilities.clj","col":1,"name-col":8,"end-col":48,"arglist-strs":["[func initial-context]"],"row":45},{"fixed-arities":[1],"end-row":59,"meta":null,"name-end-col":17,"name-end-row":53,"private":true,"name-row":53,"ns":"clojure.pprint","name":"unzip-map","defined-by":"clojure.core/defn-","filename":"clojure/pprint/utilities.clj","col":1,"name-col":8,"end-col":44,"arglist-strs":["[m]"],"doc":"Take a map that has pairs in the value slots and produce a pair of\n  maps, the first having all the first elements of the pairs and the\n  second all the second elements of the pairs","row":53},{"fixed-arities":[2],"end-row":64,"meta":null,"name-end-col":17,"name-end-row":61,"private":true,"name-row":61,"ns":"clojure.pprint","name":"tuple-map","defined-by":"clojure.core/defn-","filename":"clojure/pprint/utilities.clj","col":1,"name-col":8,"end-col":40,"arglist-strs":["[m v1]"],"doc":"For all the values, v, in the map, replace them with [v v1]","row":61},{"fixed-arities":[2],"end-row":76,"meta":null,"name-end-col":13,"name-end-row":66,"private":true,"name-row":66,"ns":"clojure.pprint","name":"rtrim","defined-by":"clojure.core/defn-","filename":"clojure/pprint/utilities.clj","col":1,"name-col":8,"end-col":11,"arglist-strs":["[s c]"],"doc":"Trim all instances of c from the end of sequence s","row":66},{"fixed-arities":[2],"end-row":87,"meta":null,"name-end-col":13,"name-end-row":78,"private":true,"name-row":78,"ns":"clojure.pprint","name":"ltrim","defined-by":"clojure.core/defn-","filename":"clojure/pprint/utilities.clj","col":1,"name-col":8,"end-col":11,"arglist-strs":["[s c]"],"doc":"Trim all instances of c from the beginning of sequence s","row":78},{"fixed-arities":[2],"end-row":98,"meta":null,"name-end-col":20,"name-end-row":89,"private":true,"name-row":89,"ns":"clojure.pprint","name":"prefix-count","defined-by":"clojure.core/defn-","filename":"clojure/pprint/utilities.clj","col":1,"name-col":8,"end-col":29,"arglist-strs":["[aseq val]"],"doc":"Return the number of times that val occurs at the start of sequence aseq,\n  if val is a seq itself, count the number of times any element of val\n  occurs at the beginning of aseq","row":89},{"end-row":104,"meta":null,"name-end-col":13,"name-end-row":100,"private":true,"name-row":100,"ns":"clojure.pprint","name":"prerr","defined-by":"clojure.core/defn-","filename":"clojure/pprint/utilities.clj","col":1,"name-col":8,"end-col":27,"arglist-strs":["[& args]"],"varargs-min-arity":0,"doc":"Println to *err*","row":100},{"end-row":110,"meta":{"private":true},"name-end-col":35,"name-end-row":106,"private":true,"name-row":106,"ns":"clojure.pprint","name":"prlabel","defined-by":"clojure.core/defmacro","filename":"clojure/pprint/utilities.clj","macro":true,"col":1,"name-col":28,"end-col":81,"arglist-strs":["[prefix arg & more-args]"],"varargs-min-arity":2,"doc":"Print args to *err* in name = value format","row":106},{"end-row":114,"meta":null,"name-end-col":26,"name-end-row":113,"name-row":113,"ns":"clojure.pprint","name":"PrettyFlush","defined-by":"clojure.core/definterface","filename":"clojure/pprint/utilities.clj","col":1,"name-col":15,"end-col":22,"row":113},{"fixed-arities":[0],"end-row":114,"meta":null,"name-end-col":17,"protocol-ns":"clojure.pprint","name-end-row":114,"name-row":114,"ns":"clojure.pprint","name":"ppflush","defined-by":"clojure.core/definterface","protocol-name":"PrettyFlush","filename":"clojure/pprint/utilities.clj","col":3,"name-col":10,"end-col":21,"arglist-strs":["[]"],"row":114},{"end-row":23,"meta":{"dynamic":true,"private":true},"name-end-col":53,"name-end-row":23,"private":true,"name-row":23,"ns":"clojure.pprint","name":"*default-page-width*","defined-by":"clojure.core/def","filename":"clojure/pprint/column_writer.clj","col":1,"name-col":33,"end-col":57,"row":23},{"fixed-arities":[2],"end-row":26,"meta":null,"name-end-col":17,"name-end-row":25,"private":true,"name-row":25,"ns":"clojure.pprint","name":"get-field","defined-by":"clojure.core/defn-","filename":"clojure/pprint/column_writer.clj","col":1,"name-col":8,"end-col":16,"arglist-strs":["[this sym]"],"row":25},{"fixed-arities":[3],"end-row":29,"meta":null,"name-end-col":17,"name-end-row":28,"private":true,"name-row":28,"ns":"clojure.pprint","name":"set-field","defined-by":"clojure.core/defn-","filename":"clojure/pprint/column_writer.clj","col":1,"name-col":8,"end-col":35,"arglist-strs":["[this sym new-val]"],"row":28},{"fixed-arities":[1],"end-row":32,"meta":null,"name-end-col":18,"name-end-row":31,"private":true,"name-row":31,"ns":"clojure.pprint","name":"get-column","defined-by":"clojure.core/defn-","filename":"clojure/pprint/column_writer.clj","col":1,"name-col":8,"end-col":25,"arglist-strs":["[this]"],"row":31},{"fixed-arities":[1],"end-row":35,"meta":null,"name-end-col":16,"name-end-row":34,"private":true,"name-row":34,"ns":"clojure.pprint","name":"get-line","defined-by":"clojure.core/defn-","filename":"clojure/pprint/column_writer.clj","col":1,"name-col":8,"end-col":26,"arglist-strs":["[this]"],"row":34},{"fixed-arities":[1],"end-row":38,"meta":null,"name-end-col":22,"name-end-row":37,"private":true,"name-row":37,"ns":"clojure.pprint","name":"get-max-column","defined-by":"clojure.core/defn-","filename":"clojure/pprint/column_writer.clj","col":1,"name-col":8,"end-col":25,"arglist-strs":["[this]"],"row":37},{"fixed-arities":[2],"end-row":42,"meta":null,"name-end-col":22,"name-end-row":40,"private":true,"name-row":40,"ns":"clojure.pprint","name":"set-max-column","defined-by":"clojure.core/defn-","filename":"clojure/pprint/column_writer.clj","col":1,"name-col":8,"end-col":7,"arglist-strs":["[this new-max]"],"row":40},{"fixed-arities":[1],"end-row":45,"meta":null,"name-end-col":18,"name-end-row":44,"private":true,"name-row":44,"ns":"clojure.pprint","name":"get-writer","defined-by":"clojure.core/defn-","filename":"clojure/pprint/column_writer.clj","col":1,"name-col":8,"end-col":26,"arglist-strs":["[this]"],"row":44},{"fixed-arities":[2],"end-row":53,"meta":null,"name-end-col":20,"name-end-row":47,"private":true,"name-row":47,"ns":"clojure.pprint","name":"c-write-char","defined-by":"clojure.core/defn-","filename":"clojure/pprint/column_writer.clj","col":1,"name-col":8,"end-col":45,"arglist-strs":["[this c]"],"row":47},{"fixed-arities":[1,2],"end-row":83,"meta":null,"name-end-col":21,"name-end-row":55,"private":true,"name-row":55,"ns":"clojure.pprint","name":"column-writer","defined-by":"clojure.core/defn-","filename":"clojure/pprint/column_writer.clj","col":1,"name-col":8,"end-col":44,"arglist-strs":["[writer]","[writer max-columns]"],"row":55}]